Workbook

Sheet START HERE
B2: Deerfield Intelligence | Operational Gap Assessment Tool
B4: Purpose: capture interview evidence once, then automatically carry it through triangulation → prioritization → sequencing.
B6: STAGE | C6: TAB | D6: WHAT YOU DO | E6: WHAT THE TOOL DOES
B7: 1. Listen | C7: 1_Evidence Log | D7: During / post interviews, add one observation per row | E7: Creates a structured evidence base with issue tags, source, evidence type and initial hypothesis.
B8: 2. Diagnose & Validate | C8: 2_Issue Register | D8: Define each emerging issue once and enter a few judgment calls (confidence, root cause, impact). | E8: Pulls interview counts, unique sources and corroborating evidence from the log; flags signal strength.
B9: 3. Prioritize | D9: Score business impact, urgency, scale dependency and effort on 1–5 scales. | E9: Calculates a weighted priority score and assigns a priority band.
B10: 4. Sequence | D10: Enter dependency, owner and timing logic. | E10: Suggests Now / Next / Later based on priority and readiness; creates the 90-day action queue.
B11: 5. Output | C11: 3_Sequence View | D11: Review output | E11: Creates final snapshot of triangulation > prioritization > sequencing
B13: Scoring guide (keep it directional — this is a decision aid, not false precision)
B15: Dimension | C15: 1 | D15: 3 | E15: 5
B16: Business impact | C16: Localized inconvenience | D16: Meaningful drag on a pod/function | E16: Material risk to DI scaling, delivery, controls or talent
B17: Urgency | C17: Can wait >6 months | D17: Should address this quarter | E17: Immediate / compounding risk
B18: Scale dependency | C18: Works similarly at 30 people | D18: Will become harder as team grows | E18: Likely breaks before / during 10→30 scale
B19: Effort | C19: Days / simple fix | D19: Several weeks / cross-functional | E19: Multi-month / complex dependency
B21: *Unique Sources helper is pre-wired to the named interviewees in the scenario. If you interview different people, replace those names
B22: in the formula or use the evidence count + your judgment; the tool is intentionally lightweight.

Sheet 1_Evidence Log
B2: Obs ID | C2: Interview / Source | D2: Role / Group | E2: Date | F2: Issue ID | G2: Category | H2: Observation | I2: Example / Evidence | J2: Evidence Type | K2: Initial Hypothesis | L2: Severity (1-5) | M2: Confidence | N2: Notes
B3: OBS-001 | C3: Elena Rodriguez | D3: HR / Central Function | E3: 2026-09-18 | F3: ORG-01 | G3: Operating Model & Decision Rights | H3: HR support for DI is capacity-constrained and largely reactive. | I3: Elena estimates only 20–25% of her time is available for DI; coordination is mainly a monthly meeting with David, after issues have already occurred. | J3: Metric / data | K3: DI lacks a sufficiently frequent HR–Operations interface and a counterpart who can translate team needs into central processes. | L3: 4 | M3: High | N3: Elena's capacity estimate and current cadence; validate with David and DI leads.
B4: =IF(C4="","","OBS-"&TEXT(ROW()-2,"000")) -> OBS-002 | C4: Elena Rodriguez | D4: HR / Central Function | E4: 2026-09-18 | F4: WFP-01 | G4: Workforce Planning | H4: DI does not have a clear, sequenced workforce plan for growth from 10 to 30. | I4: HR has no roadmap specifying roles, timing or sequence; searches can change level or skill profile after sourcing begins, and some stall when projects are deprioritized. | J4: Repeated pattern | K4: Workforce needs are triggered reactively by immediate project pressure rather than an agreed capacity and capability plan. | L4: 5 | M4: High | N4: Strong single-source pattern; validate frequency and examples with David and pod leads.
B5: =IF(C5="","","OBS-"&TEXT(ROW()-2,"000")) -> OBS-003 | C5: Elena Rodriguez | D5: HR / Central Function | E5: 2026-09-18 | F5: HIR-01 | G5: Hiring | H5: The recruiting process is too slow and ad hoc to support planned hiring volume. | I5: A recent ML engineer search took four months; two strong candidates were lost because DI could not provide a timeline. | J5: Direct example | K5: DI lacks a standardized, actively managed recruiting funnel with clear stages, service levels and candidate ownership. | L5: 5 | M5: High | N5: Material quantitative example; seek ATS data to confirm baseline cycle time and conversion.
B6: =IF(C6="","","OBS-"&TEXT(ROW()-2,"000")) -> OBS-004 | C6: Elena Rodriguez | D6: HR / Central Function | E6: 2026-09-18 | F6: HIR-01 | G6: Hiring | H6: Interview scheduling and stage-by-stage execution create avoidable delay. | I6: It typically takes one to two weeks to secure three to four interview slots; rounds are booked sequentially and feedback waits add further gaps. | J6: Metric / data | K6: Unreserved interviewer capacity, sequential scheduling and unclear execution ownership extend time-to-hire. | L6: 4 | M6: High | N6: Specific timing estimate from process owner; validate against recent requisitions.
B7: =IF(C7="","","OBS-"&TEXT(ROW()-2,"000")) -> OBS-005 | C7: Elena Rodriguez | D7: HR / Central Function | E7: 2026-09-18 | F7: HIR-01 | G7: Hiring | H7: David is a single point of dependency for hiring decisions and final interviews. | I7: David makes the final call on every hire; when his calendar is constrained, Intelligence recruiting stops even when the team supports a candidate. | J7: Repeated pattern | K7: Hiring decision rights have not been delegated or supported by a sufficiently trusted assessment process. | L7: 5 | M7: Medium | N7: Elena's recurring observation; test David's rationale and appetite to delegate by role level.
B8: =IF(C8="","","OBS-"&TEXT(ROW()-2,"000")) -> OBS-006 | C8: Elena Rodriguez | D8: HR / Central Function | E8: 2026-09-18 | G8: Strength / Context | H8: DI's hiring model preserves a strong quality bar and is effective at closing candidates once they meet the team. | I8: Elena reports candidates are impressed by David, the team and the work; David is decisive once engaged, and engineers protect technical and cultural standards. | J8: Perception / opinion | K8: The recruiting redesign should preserve the close and hiring bar while removing upstream planning and execution friction. | L8: 3 | M8: Medium | N8: Positive context only; excluded from issue counts and retained to define what the redesign must preserve.
B9: =IF(C9="","","OBS-"&TEXT(ROW()-2,"000")) -> OBS-007 | C9: Elena Rodriguez | D9: HR / Central Function | E9: 2026-09-18 | F9: ONB-01 | G9: Onboarding | H9: Technical onboarding lacks an end-to-end owner and standard access checklist. | I9: One new hire could not access the code repository for three weeks; hardware, base accounts and specialized access are split across IT and different DI team members. | J9: Direct example | K9: Fragmented provisioning ownership and tribal knowledge prevent new hires from becoming productive quickly. | L9: 5 | M9: High | N9: Concrete example; validate whether this occurred once or reflects typical access lead times.
B10: =IF(C10="","","OBS-"&TEXT(ROW()-2,"000")) -> OBS-008 | C10: Elena Rodriguez | D10: HR / Central Function | E10: 2026-09-18 | F10: ONB-02 | G10: Onboarding | H10: New hires lack a structured first-30-day plan and integration into the broader firm. | I10: After standard HR orientation, new hires largely 'sink or swim'; there is no formal 30-60-90 plan or stakeholder map, and they remain socially and operationally isolated from Deerfield. | J10: Repeated pattern | K10: DI onboarding covers basic administration but not role ramp-up, organizational context or cross-firm relationships. | L10: 4 | M10: Medium | N10: Elena's assessment; test directly with recent hires and managers.
B11: =IF(C11="","","OBS-"&TEXT(ROW()-2,"000")) -> OBS-009 | C11: Elena Rodriguez | D11: HR / Central Function | E11: 2026-09-18 | F11: WFP-02 | G11: Workforce Planning | H11: DI's flat structure will not scale to 30 people without a capable middle layer. | I11: Most employees currently rely on David; Elena expects pod or functional leads, explicit spans of control and manager training will be needed before the team reaches roughly 15–20. | J11: Perception / opinion | K11: DI has not yet designed the leadership structure and management capability required for the next stage of growth. | L11: 5 | M11: Medium | N11: Forward-looking risk rather than a current failure; validate against current reporting lines and hiring plan.
B12: =IF(C12="","","OBS-"&TEXT(ROW()-2,"000")) -> OBS-010 | C12: Elena Rodriguez | D12: HR / Central Function | E12: 2026-09-18 | F12: ORG-01 | G12: Organization & Performance | H12: Roles, accountabilities and decision rights are informal and sometimes ambiguous. | I12: Elena believes different team members could name different owners for the same data pipeline or product feature; in-seat expectations are not documented beyond titles. | J12: Perception / opinion | K12: Scrappy shared ownership is obscuring accountability and will create duplication, escalation and performance-management difficulty as DI grows. | L12: 4 | M12: Medium | N12: Hypothesis requires corroboration from delivery examples and pod interviews.
B13: =IF(C13="","","OBS-"&TEXT(ROW()-2,"000")) -> OBS-011 | C13: Elena Rodriguez | D13: HR / Central Function | E13: 2026-09-18 | F13: ORG-02 | G13: Organization & Performance | H13: Performance management is informal and insufficiently documented. | I13: Firm-wide reviews are treated as a check-box exercise; feedback is mainly verbal, leaving limited support for compensation differentiation, promotion decisions or performance action. | J13: Repeated pattern | K13: DI has not adapted the firm's performance framework into a lightweight process that fits an agile technical team. | L13: 4 | M13: Medium | N13: Validate employee experience and review completion/document quality.
B14: =IF(C14="","","OBS-"&TEXT(ROW()-2,"000")) -> OBS-012 | C14: Elena Rodriguez | D14: HR / Central Function | E14: 2026-09-18 | F14: WFP-03 | G14: Workforce Planning | H14: Levels and career paths are not defined for DI technical talent. | I14: There is no documented progression from Senior to Staff or Lead and no competency matrix; advancement depends heavily on David's judgment and visibility. | J14: Perception / opinion | K14: Lack of transparent growth paths may become a retention risk as the team expands, despite strong current culture and talent quality. | L14: 4 | M14: Medium | N14: Emerging risk, not evidence of current attrition; test with employees and exit/engagement data.
B15: =IF(C15="","","OBS-"&TEXT(ROW()-2,"000")) -> OBS-013 | C15: Elena Rodriguez | D15: HR / Central Function | E15: 2026-09-18 | F15: INT-01 | G15: DI-Deerfield Integration | H15: DI operates as a silo from the traditional investment organization, weakening shared context and support for resource requests. | I15: Elena observes an 'us versus them' dynamic, limited positive touchpoints and weak visibility into DI's value; she links this to harder approval of compensation and resources. | J15: Perception / opinion | K15: DI lacks a deliberate stakeholder-engagement and value-communication mechanism with the broader firm. | L15: 4 | M15: Medium | N15: Important but perception-led; test with investment stakeholders and examples of delayed or rejected requests.
B16: =IF(C16="","","OBS-"&TEXT(ROW()-2,"000")) -> OBS-014 | C16: Elena Rodriguez | D16: HR / Central Function | E16: 2026-09-18 | F16: ORG-03 | G16: Organization & Performance | H16: Annual compensation cycles limit DI's ability to respond to fast-moving retention risks. | I16: When a key engineer receives a competing offer mid-year, Elena must pursue an out-of-cycle adjustment through an exception process. | J16: Repeated pattern | K16: DI lacks a defined, evidence-based path for time-sensitive compensation decisions outside the annual cycle. | L16: 4 | M16: Medium | N16: Separate compensation issue; validate frequency, decision time and outcomes with HR and the Compensation Committee.
B17: =IF(C17="","","OBS-"&TEXT(ROW()-2,"000")) -> OBS-015 | C17: Elena Rodriguez | D17: HR / Central Function | E17: 2026-09-18 | F17: WFP-04 | G17: Workforce Planning | H17: Firm-wide titles and pay bands do not map cleanly to DI's technical roles. | I17: Traditional definitions of Vice President, Director and Senior Associate do not consistently reflect technology-market titles, responsibilities or compensation. | J17: Repeated pattern | K17: DI lacks a technology-specific job architecture mapped back to Deerfield's firm-wide levels and compensation framework. | L17: 4 | M17: Medium | N17: Separate job-architecture issue; validate with current role mapping and external benchmarks.
B18: =IF(C18="","","OBS-"&TEXT(ROW()-2,"000")) -> OBS-016 | C18: Elena Rodriguez | D18: HR / Central Function | E18: 2026-09-18 | F18: CORP-01 | G18: Corporate Interfaces | H18: Standard procurement processes can delay access to specialized software and data tools. | I18: Elena reports that approval of a new tool or specialized data subscription can take weeks through standard corporate channels. | J18: Repeated pattern | K18: DI lacks a proportionate, clearly routed approval path for time-sensitive technology and data purchases. | L18: 4 | M18: Medium | N18: Separate procurement issue; triangulate with IT/SecOps and Finance/Procurement.
B19: =IF(C19="","","OBS-"&TEXT(ROW()-2,"000")) -> OBS-017 | C19: Elena Rodriguez | D19: HR / Central Function | E19: 2026-09-18 | F19: HIR-02 | G19: Hiring | H19: Firm-wide office expectations may constrain DI's access to specialized AI talent. | I19: DI competes with employers offering fully remote roles, making office-location expectations a recurring point of negotiation with candidates. | J19: Repeated pattern | K19: DI has not defined when talent scarcity justifies role-specific flexibility within Deerfield's workplace policy. | L19: 3 | M19: Medium | N19: Separate hiring-policy issue; validate actual candidate losses and role/location requirements.
B20: =IF(C20="","","OBS-"&TEXT(ROW()-2,"000")) -> OBS-018 | C20: Elena Rodriguez | D20: HR / Central Function | E20: 2026-09-18 | F20: ORG-01 | G20: Operating Model & Decision Rights | H20: Ownership between HR and DI is blurred, creating handoffs and work in the wrong function. | I20: HR coordinates technical interview calendars and is asked to ensure technical setup, while DI sometimes handles compensation guidance or performance issues without early HR involvement. | J20: Repeated pattern | K20: DI needs a single operational front door with explicit decision rights: Operations owns team context and execution; HR owns framework, fairness, compliance and sensitive employee matters. | L20: 4 | M20: High | N20: Elena proposed a weekly tactical sync and shared tracker as the working interface.
B21: =IF(C21="","","OBS-"&TEXT(ROW()-2,"000")) -> OBS-019 | C21: James Okonkwo | D21: Finance / Central Function | E21: 2026-09-18 | G21: Strength / Context | H21: DI is viewed as cost-conscious, and David engages constructively on financial trade-offs. | I21: James reports that the team is thoughtful about proposed purchases and that David listens when Finance challenges spend. | J21: Perception / opinion | K21: The finance operating model should improve visibility and control without assuming DI is culturally undisciplined about cost. | L21: 3 | M21: Medium | N21: Positive context only; excluded from issue counts and retained to define what the redesign must preserve.
B22: =IF(C22="","","OBS-"&TEXT(ROW()-2,"000")) -> OBS-020 | C22: James Okonkwo | D22: Finance / Central Function | E22: 2026-09-18 | F22: FIN-01 | G22: Financial Planning & Spend Management | H22: DI's annual budget is based on rough historical estimates rather than a costed delivery and growth roadmap. | I22: The budget uses prior-year spend plus buffers for hiring, data and cloud; new projects and their resource needs are not translated into line items before work begins. | J22: Repeated pattern | K22: DI lacks a rolling driver-based financial model connecting headcount, roadmap choices and major technology consumption to expected spend. | L22: 5 | M22: High | N22: Corroborate with the current budget model, hiring plan and project roadmap.
B23: =IF(C23="","","OBS-"&TEXT(ROW()-2,"000")) -> OBS-021 | C23: James Okonkwo | D23: Finance / Central Function | E23: 2026-09-18 | F23: FIN-01 | G23: Financial Planning & Spend Management | H23: Finance receives too little forward visibility to forecast DI's major spending needs. | I23: James wants a rolling six-month outlook and 30–60 days' notice for major expenses; current visibility is often about two weeks and triggered by urgent payment requests. | J23: Metric / data | K23: DI lacks a regular reforecasting process and a mechanism for translating roadmap changes into financial implications. | L23: 5 | M23: High | N23: Specific current- and future-state timing from the Finance liaison; validate with recent requests.
B24: =IF(C24="","","OBS-"&TEXT(ROW()-2,"000")) -> OBS-022 | C24: James Okonkwo | D24: Finance / Central Function | E24: 2026-09-18 | F24: FIN-02 | G24: Financial Planning & Spend Management | H24: Cloud spend is monitored too late to prevent material budget variance. | I24: DI finished the prior quarter approximately 40% over its cloud budget, and Finance identified the overage only after the quarter had ended. | J24: Direct example | K24: DI lacks timely cloud-cost monitoring, thresholds and accountable operational follow-up during the reporting period. | L24: 5 | M24: High | N24: Direct quantified example; validate against AWS/GCP billing and the quarterly forecast.
B25: =IF(C25="","","OBS-"&TEXT(ROW()-2,"000")) -> OBS-023 | C25: James Okonkwo | D25: Finance / Central Function | E25: 2026-09-18 | F25: FIN-02 | G25: Financial Planning & Spend Management | H25: DI's cloud-cost exposure can change rapidly without an early-warning mechanism. | I25: AWS and GCP currently cost about $30,000 per month; James believes usage can double quickly when new infrastructure is launched or large jobs continue running. | J25: Metric / data | K25: Variable infrastructure consumption is not paired with weekly burn-rate monitoring, anomaly alerts or named ownership for investigating spikes. | L25: 5 | M25: High | N25: Current spend estimate plus risk assessment; triangulate with technical owners and cloud-cost data.
B26: =IF(C26="","","OBS-"&TEXT(ROW()-2,"000")) -> OBS-024 | C26: James Okonkwo | D26: Finance / Central Function | E26: 2026-09-18 | F26: BVC-01 | G26: Business Case & Value Management | H26: DI cannot consistently attribute spend to projects or workstreams. | I26: Data, cloud and other costs are largely reported in aggregate, so Finance cannot explain which initiatives caused increases or whether the spend was worthwhile. | J26: Repeated pattern | K26: DI lacks project-level cost allocation and a lightweight method for linking consumption to the work that generated it. | L26: 4 | M26: High | N26: Validate feasible allocation granularity with Finance and technical leads; avoid false precision.
B27: =IF(C27="","","OBS-"&TEXT(ROW()-2,"000")) -> OBS-025 | C27: James Okonkwo | D27: Finance / Central Function | E27: 2026-09-18 | F27: BVC-01 | G27: Business Case & Value Management | H27: Partner reporting describes DI's inputs and costs but does not connect them to business or investment outcomes. | I27: Current reporting lists salaries, data and cloud costs; partners are beginning to ask what several million dollars of annual spend is buying and whether specific data investments improved decisions. | J27: Repeated pattern | K27: DI lacks a value narrative and supporting measures that connect major investments to delivery, investment insight or portfolio impact. | L27: 5 | M27: Medium | N27: Partner questions are reported by James; validate directly with partners and avoid claiming causal investment returns without evidence.
B28: =IF(C28="","","OBS-"&TEXT(ROW()-2,"000")) -> OBS-026 | C28: James Okonkwo | D28: Finance / Central Function | E28: 2026-09-18 | F28: CORP-01 | G28: Corporate Interfaces | H28: New tools and vendor commitments can be initiated before Finance reviews the need, budget or terms. | I28: Team members may start a subscription or free trial and Finance learns of the commitment only when an invoice or credit-card charge appears. | J28: Repeated pattern | K28: DI lacks a proportionate pre-commitment intake and approval path that is fast enough for the team to use consistently. | L28: 5 | M28: High | N28: Corroborates Elena's concern that the standard path does not fit DI, while showing the resulting bypass behavior.
B29: =IF(C29="","","OBS-"&TEXT(ROW()-2,"000")) -> OBS-027 | C29: James Okonkwo | D29: Finance / Central Function | E29: 2026-09-18 | F29: CORP-01 | G29: Corporate Interfaces | H29: Procurement authority and approval thresholds are unclear. | I29: James cannot identify who may approve a $5,000 annual tool or when Finance's receipt of an invoice becomes the de facto approval point. | J29: Direct example | K29: Decision rights and spend thresholds are not explicit across DI Operations, technical leaders, Finance and the corporate CFO. | L29: 5 | M29: High | N29: Direct ownership gap; validate current delegation-of-authority policy before designing thresholds.
B30: =IF(C30="","","OBS-"&TEXT(ROW()-2,"000")) -> OBS-028 | C30: James Okonkwo | D30: Finance / Central Function | E30: 2026-09-18 | F30: VEN-01 | G30: Vendor & Contract Management | H30: DI has duplicate and potentially underused vendor subscriptions. | I30: Finance found three data-visualization tools being paid for simultaneously because different employees had established them at different times. | J30: Direct example | K30: DI lacks a complete vendor inventory, usage review and periodic rationalization process. | L30: 4 | M30: High | N30: Concrete overlap example; a full vendor audit would establish the scale of waste.
B31: =IF(C31="","","OBS-"&TEXT(ROW()-2,"000")) -> OBS-029 | C31: James Okonkwo | D31: Finance / Central Function | E31: 2026-09-18 | F31: VEN-01 | G31: Vendor & Contract Management | H31: Vendor contracts and commercial terms are fragmented across people and locations. | I31: James has found contracts signed by former employees and has had to investigate who authorized them, whether the tools remain in use and when they renew. | J31: Repeated pattern | K31: DI lacks a centralized contract repository with current business owners, costs, terms and renewal dates. | L31: 5 | M31: High | N31: Recurring observation from the person performing the manual reconciliation.
B32: =IF(C32="","","OBS-"&TEXT(ROW()-2,"000")) -> OBS-030 | C32: James Okonkwo | D32: Finance / Central Function | E32: 2026-09-18 | F32: VEN-01 | G32: Vendor & Contract Management | H32: DI is exposed to avoidable renewal and termination risk. | I32: Large data contracts can require 90 days' notice, creating a risk of default renewal when ownership is unclear or cancellation windows are missed. | J32: Repeated pattern | K32: Vendor lifecycle management does not reliably trigger timely usage, value and renewal decisions. | L32: 4 | M32: High | N32: Validate notice periods and auto-renewal exposure through the contract audit.
B33: =IF(C33="","","OBS-"&TEXT(ROW()-2,"000")) -> OBS-031 | C33: James Okonkwo | D33: Finance / Central Function | E33: 2026-09-18 | F33: VEN-01 | G33: Vendor & Contract Management | H33: Business ownership for vendors is unclear, causing renewal by default. | I33: For a data-provider renewal, Finance may be redirected among David, Priya and Marcus without anyone clearly accountable for deciding whether the service is still required. | J33: Direct example | K33: DI has not assigned one accountable business owner for each vendor relationship and renewal decision. | L33: 4 | M33: High | N33: Specific decision-path example; test whether it recurs across the vendor portfolio.
... B36: =IF(C36="","","OBS-"&TEXT(ROW()-2,"000")) -> OBS-034 | C36: James Okonkwo | D36: Finance / Central Function | E36: 2026-09-18 | F36: FIN-01 | G36: Financial Planning & Spend Management | H36: The current finance-control model depends on manual effort that will not scale. | I36: James spends about 20% of his time on DI and estimates a personally enforced manual gatekeeping workaround would remain viable for only three to six months or until roughly 15–20 employees. | J36: Metric / data | K36: Without an Operations owner and shared controls, Finance cannot absorb the additional coordination and monitoring load created by growth to 30. | L36: 5 | M36: High | N36: Specific capacity and scalability estimate from the Finance liaison.
B37: =IF(C37="","","OBS-"&TEXT(ROW()-2,"000")) -> OBS-035 | C37: Marcus Thompson | D37: Portfolio Enablement Pod | E37: 2026-09-18 | G37: Strength / Context | H37: Marcus's pod combines direct portfolio-company access, strong technical autonomy and rapid delivery. | I37: Deerfield's investor relationship gives the pod access to portfolio executives; David does not micromanage technical decisions, and Marcus cited a tool that accelerated a clinical-trial process by 30%. | J37: Direct example | K37: The operating model should add coordination and predictability while preserving direct client access, technical autonomy and speed. | L37: 4 | M37: Medium | N37: Positive context only; excluded from issue counts and retained to define what the redesign must preserve.
B38: =IF(C38="","","OBS-"&TEXT(ROW()-2,"000")) -> OBS-036 | C38: Marcus Thompson | D38: Portfolio Enablement Pod | E38: 2026-09-18 | F38: PIP-01 | G38: Portfolio Intake & Prioritization | H38: DI lacks a controlled front door for portfolio-support requests. | I38: Requests arrive through Partners, Principals, portfolio-company executives, David or informal Slack messages; there is no consistent evaluation or intake step. | J38: Repeated pattern | K38: Open access without structured intake prevents DI from comparing demand against strategy, impact and available capacity. | L38: 5 | M38: High | N38: Validate request volume and channels with Investment Partners and David.
B39: =IF(C39="","","OBS-"&TEXT(ROW()-2,"000")) -> OBS-037 | C39: Marcus Thompson | D39: Portfolio Enablement Pod | E39: 2026-09-18 | F39: PIP-01 | G39: Portfolio Intake & Prioritization | H39: Competing requests are resolved through urgency and influence rather than explicit trade-offs. | I39: Marcus described prioritization as 'loudest voice wins'; urgent work displaces planned work without a formal decision or communication to the affected stakeholder. | J39: Repeated pattern | K39: DI lacks transparent prioritization criteria and a mechanism for making and communicating trade-off decisions. | L39: 5 | M39: High | N39: Strong repeated pattern; triangulate how David and Investment Partners perceive current prioritization.
B40: =IF(C40="","","OBS-"&TEXT(ROW()-2,"000")) -> OBS-038 | C40: Marcus Thompson | D40: Portfolio Enablement Pod | E40: 2026-09-18 | F40: PIP-01 | G40: Portfolio Intake & Prioritization | H40: Urgent requests create material disruption beyond their initial estimate. | I40: A two-day physician-targeting request expanded to two weeks, stalled a rare-disease patient-matching project, frustrated the original company and required ten days of late work to recover. | J40: Direct example | K40: DI accepts urgent work without adequately testing scope, dependency and displacement consequences. | L40: 5 | M40: High | N40: Concrete displacement example supporting the intake and trade-off issue.
B41: =IF(C41="","","OBS-"&TEXT(ROW()-2,"000")) -> OBS-039 | C41: Marcus Thompson | D41: Portfolio Enablement Pod | E41: 2026-09-18 | F41: SCP-01 | G41: Scoping & Delivery | H41: Projects begin without sufficiently clear scope, stakeholder obligations or a definition of done. | I41: One six-week engagement expanded to fourteen weeks; initial releases are followed by repeated feature requests and a long tail of support because completion criteria were not agreed. | J41: Direct example | K41: DI lacks a lightweight engagement charter defining outcomes, boundaries, milestones, client inputs and transition or exit criteria. | L41: 5 | M41: High | N41: Separate from prioritization: this concerns how accepted work is scoped and closed.
B42: =IF(C42="","","OBS-"&TEXT(ROW()-2,"000")) -> OBS-040 | C42: Marcus Thompson | D42: Portfolio Enablement Pod | E42: 2026-09-18 | F42: CAP-01 | G42: Capacity Planning | H42: Pod capacity and delivery commitments are based largely on judgment rather than visible workload data. | I42: Marcus cannot readily quantify time by project or see whether Priya's pod is at 50% or 150% capacity; commitments are made before cross-pod capacity is known. | J42: Repeated pattern | K42: DI lacks a shared, sufficiently lightweight capacity view to support credible commitments and data-backed trade-offs. | L42: 5 | M42: High | N42: Validate what utilization data can be captured without burdensome time tracking.
B43: =IF(C43="","","OBS-"&TEXT(ROW()-2,"000")) -> OBS-041 | C43: Marcus Thompson | D43: Portfolio Enablement Pod | E43: 2026-09-18 | F43: XPD-01 | G43: Cross-Pod Coordination | H43: Cross-pod dependencies are identified and managed too late. | I43: Marcus requests pipelines or schema changes through Slack; required work may not be on Priya's backlog, leaving his delivery waiting or forcing timeline changes. | J43: Repeated pattern | K43: DI lacks integrated roadmaps and an explicit process to surface, accept and sequence cross-pod dependencies before commitments are made. | L43: 5 | M43: High | N43: Marcus identified this as one of the two highest-priority operational issues.
B44: =IF(C44="","","OBS-"&TEXT(ROW()-2,"000")) -> OBS-042 | C44: Marcus Thompson | D44: Portfolio Enablement Pod | E44: 2026-09-18 | F44: XPD-01 | G44: Cross-Pod Coordination | H44: Unaligned pod priorities make end-to-end delivery dates unreliable. | I44: A feature promised in two weeks took six weeks after a required data pipeline was delayed; Marcus had committed externally without Priya's team agreeing the dependency. | J44: Direct example | K44: Each pod maintains its own priorities without a shared commitment point for projects requiring both teams. | L44: 5 | M44: High | N44: Concrete example; compare with Priya's account of the same operating mechanism.
B45: =IF(C45="","","OBS-"&TEXT(ROW()-2,"000")) -> OBS-043 | C45: Marcus Thompson | D45: Portfolio Enablement Pod | E45: 2026-09-18 | F45: ORG-01 | G45: Organization & Performance | H45: End-to-end accountability becomes unclear when delivery crosses pod or organizational boundaries. | I45: Marcus remains accountable to the portfolio company for timeline or data-quality failures but lacks authority over Priya's backlog, Compliance review or portfolio-company inputs. | J45: Repeated pattern | K45: Functional ownership exists inside pods, but no one owns the integrated outcome and escalation across contributors. | L45: 5 | M45: High | N45: Corroborates Elena's broader role-and-accountability issue with a concrete delivery context.
B46: =IF(C46="","","OBS-"&TEXT(ROW()-2,"000")) -> OBS-044 | C46: Marcus Thompson | D46: Portfolio Enablement Pod | E46: 2026-09-18 | F46: PMO-01 | G46: Portfolio Visibility & Operating Rhythm | H46: DI lacks a shared source of truth for projects, status, rationale, dependencies and risks. | I46: Status is held in Marcus's memory, Slack and partial project documents; David, Priya and Partners must ask Marcus directly for updates and may receive different versions. | J46: Repeated pattern | K46: DI lacks a consistently maintained portfolio view that allows stakeholders to self-serve reliable project information. | L46: 4 | M46: High | N46: Tool choice is secondary; the main gap is common data standards and update discipline.
B47: =IF(C47="","","OBS-"&TEXT(ROW()-2,"000")) -> OBS-045 | C47: Marcus Thompson | D47: Portfolio Enablement Pod | E47: 2026-09-18 | F47: PMO-01 | G47: Portfolio Visibility & Operating Rhythm | H47: Existing DI forums emphasize status reporting rather than forward-looking coordination and decisions. | I47: The weekly DI meeting is mainly rapid-fire updates; there is no regular tactical forum for resolving dependencies, reviewing capacity or escalating risks before they affect delivery. | J47: Repeated pattern | K47: DI's operating cadence does not convert portfolio information into cross-pod decisions and early intervention. | L47: 4 | M47: High | N47: Distinguish the required execution forum from existing pod stand-ups and high-level updates.
B48: =IF(C48="","","OBS-"&TEXT(ROW()-2,"000")) -> OBS-046 | C48: Marcus Thompson | D48: Portfolio Enablement Pod | E48: 2026-09-18 | F48: CORP-02 | G48: Corporate Interfaces | H48: Compliance and legal review timelines are opaque and unpredictable. | I48: External deployments may receive review in three days or three weeks; submissions can sit without visible status, preventing Marcus from providing credible launch dates. | J48: Repeated pattern | K48: DI lacks a predictable intake, status and service-level mechanism for recurring Compliance/Legal reviews. | L48: 5 | M48: High | N48: Validate with Sarah, including review types, capacity and risk-based differentiation.
B49: =IF(C49="","","OBS-"&TEXT(ROW()-2,"000")) -> OBS-047 | C49: Marcus Thompson | D49: Portfolio Enablement Pod | E49: 2026-09-18 | F49: CORP-03 | G49: Corporate Interfaces | H49: Security and data-access enablement requires excessive manual coordination. | I49: Marcus reports that security clearance, VPN or data-access setup can require up to three weeks of email follow-up before technical work begins. | J49: Repeated pattern | K49: DI lacks a clearly routed, risk-appropriate access pathway for portfolio-support engagements with external deadlines. | L49: 4 | M49: Medium | N49: Triangulate with IT/SecOps and distinguish Deerfield-controlled delays from portfolio-company delays.
... B54: =IF(C54="","","OBS-"&TEXT(ROW()-2,"000")) -> OBS-052 | C54: Marcus Thompson | D54: Portfolio Enablement Pod | E54: 2026-09-18 | F54: BVC-01 | G54: Business Case & Value Management | H54: DI lacks a consistent view of project impact to inform prioritization and stakeholder confidence. | I54: Marcus wants project outcomes such as time or cost saved visible alongside the work queue so new requests can be compared against demonstrated impact. | J54: Perception / opinion | K54: DI's portfolio information emphasizes activity and status more than realized outcomes, limiting evidence-based prioritization and value communication. | L54: 4 | M54: Medium | N54: Corroborates James's reporting concern; validate available outcome measures with portfolio companies and Investment Partners.
B55: =IF(C55="","","OBS-"&TEXT(ROW()-2,"000")) -> OBS-053 | C55: Priya Sharma | D55: AI Investment Systems Pod | E55: 2026-09-18 | G55: Strength / Context | H55: Priya's pod has strong technical autonomy, rapid delivery and a direct feedback loop with investment users. | I55: David provides outcome-oriented problems without micromanaging the technical solution; Priya cited an FDA-meeting tool that analysts used in real investment decisions shortly after launch. | J55: Direct example | K55: The operating model should improve focus and coordination while preserving technical autonomy, direct user feedback and delivery speed. | L55: 4 | M55: Medium | N55: Positive context only; excluded from issue counts and retained to define what the redesign must preserve.
B56: =IF(C56="","","OBS-"&TEXT(ROW()-2,"000")) -> OBS-054 | C56: Priya Sharma | D56: AI Investment Systems Pod | E56: 2026-09-18 | F56: ORG-01 | G56: Operating Model & Decision Rights | H56: The pod lead spends substantial time on work outside technical leadership. | I56: Priya tracked approximately 30% of her time on vendor follow-up, budget discussions, IT coordination, project status, onboarding and other administration. | J56: Metric / data | K56: Missing operational ownership shifts recurring coordination and administrative work onto scarce technical leadership capacity. | L56: 5 | M56: High | N56: Corroborates Marcus's operational-leverage issue with a quantified time estimate.
B57: =IF(C57="","","OBS-"&TEXT(ROW()-2,"000")) -> OBS-055 | C57: Priya Sharma | D57: AI Investment Systems Pod | E57: 2026-09-18 | F57: ONB-01 | G57: Onboarding | H57: Technical onboarding depends on manual guidance and incomplete documentation. | I57: A new engineer from Palantir took about three weeks to become productive; Priya manually walked him through systems, environment setup and deployment because the relevant materials were unavailable or outdated. | J57: Direct example | K57: DI lacks role-based technical onboarding, ready access and a documented engineering setup path. | L57: 5 | M57: High | N57: Corroborates Elena's three-week access/productivity example from a pod-lead perspective.
B58: =IF(C58="","","OBS-"&TEXT(ROW()-2,"000")) -> OBS-056 | C58: Priya Sharma | D58: AI Investment Systems Pod | E58: 2026-09-18 | F58: PLC-01 | G58: Product Lifecycle & Knowledge | H58: Technical knowledge and operating guidance are fragmented and often outdated. | I58: Priya described sparse tribal knowledge and READMEs that can be six months out of date; deployment scripts, data dictionaries and core-system guidance are difficult for new engineers to locate. | J58: Repeated pattern | K58: DI lacks minimum documentation standards, a clear knowledge structure and protected capacity for content experts to maintain critical technical guidance. | L58: 4 | M58: High | N58: Corroborates Marcus; Operations should own scaffolding and cadence, while engineers own technical content.
B59: =IF(C59="","","OBS-"&TEXT(ROW()-2,"000")) -> OBS-057 | C59: Priya Sharma | D59: AI Investment Systems Pod | E59: 2026-09-18 | F59: CORP-01 | G59: Corporate Interfaces | H59: Vendor procurement lacks one accountable owner and visible end-to-end workflow. | I59: Priya coordinates budget approval, Legal/Data Privacy, Security, execution and access through email and Slack; she cannot see where a request sits without repeatedly chasing each function. | J59: Repeated pattern | K59: DI lacks one operational front door, standard submission requirements, visible stages and active orchestration across Finance, Legal and IT. | L59: 5 | M59: High | N59: Strong corroboration of the fit-for-purpose procurement issue identified by Elena and James.
B60: =IF(C60="","","OBS-"&TEXT(ROW()-2,"000")) -> OBS-058 | C60: Priya Sharma | D60: AI Investment Systems Pod | E60: 2026-09-18 | F60: FIN-01 | G60: Financial Planning & Spend Management | H60: Pod-level budget availability is unclear to the people making tool and resource decisions. | I60: Priya cannot readily state her pod's available budget for new tools or headcount and often requires James and David to determine whether a request can proceed. | J60: Perception / opinion | K60: DI's financial plan is not translated into accessible pod-level guardrails that support timely operating decisions. | L60: 4 | M60: Medium | N60: Corroborates the financial-planning gap; validate whether formal budgets exist but are not communicated.
B61: =IF(C61="","","OBS-"&TEXT(ROW()-2,"000")) -> OBS-059 | C61: Priya Sharma | D61: AI Investment Systems Pod | E61: 2026-09-18 | F61: PIP-01 | G61: Portfolio Intake & Prioritization | H61: The investment-systems pod lacks a controlled intake and prioritization process. | I61: Requests arrive from analysts, David and Marcus through Slack or conversation; there is no front door, visible queue or common evaluation process. | J61: Repeated pattern | K61: Unstructured demand prevents DI from comparing requests consistently against strategy, impact, dependencies and capacity. | L61: 5 | M61: High | N61: Directly corroborates Marcus despite serving a different internal customer group.
B62: =IF(C62="","","OBS-"&TEXT(ROW()-2,"000")) -> OBS-060 | C62: Priya Sharma | D62: AI Investment Systems Pod | E62: 2026-09-18 | F62: PIP-01 | G62: Portfolio Intake & Prioritization | H62: Priority changes regularly displace planned work without explicit trade-off management. | I62: Urgent requests cause engineers to stop partially completed work, often without communicating the resulting delay; Priya described a Marcus dependency that displaced a clinical-trial summarization project for a week. | J62: Direct example | K62: DI lacks a protected planning horizon and a decision mechanism that makes the consequences of priority changes visible. | L62: 5 | M62: High | N62: Mirrors Marcus's displacement example from the supplying pod's perspective.
B63: =IF(C63="","","OBS-"&TEXT(ROW()-2,"000")) -> OBS-061 | C63: Priya Sharma | D63: AI Investment Systems Pod | E63: 2026-09-18 | F63: PMO-01 | G63: Portfolio Visibility & Operating Rhythm | H63: The pod has no shared roadmap, backlog or project-tracking source of truth. | I63: The roadmap is largely a wish list in David's head, Slack threads and Priya's personal notes; there is no quarterly planning process or public, maintained backlog. | J63: Repeated pattern | K63: DI lacks a lightweight planning and portfolio-management discipline that makes committed, deferred and blocked work visible. | L63: 5 | M63: High | N63: Strong corroboration of Marcus's portfolio-visibility issue.
B64: =IF(C64="","","OBS-"&TEXT(ROW()-2,"000")) -> OBS-062 | C64: Priya Sharma | D64: AI Investment Systems Pod | E64: 2026-09-18 | F64: XPD-01 | G64: Cross-Pod Coordination | H64: Marcus can commit Priya's capacity before her pod has accepted the dependency. | I64: Marcus promised a portfolio-company feature requiring Priya's team; she learned of it one week before the deadline and the team worked late to deliver. | J64: Direct example | K64: Cross-pod work is not jointly scoped, capacity-checked and committed before external dates are communicated. | L64: 5 | M64: High | N64: Corroborates Marcus's example while confirming that the late request affected Priya's team.
B65: =IF(C65="","","OBS-"&TEXT(ROW()-2,"000")) -> OBS-063 | C65: Priya Sharma | D65: AI Investment Systems Pod | E65: 2026-09-18 | F65: XPD-01 | G65: Cross-Pod Coordination | H65: Shared technical dependencies and changes are not consistently visible across pods. | I65: Priya may refactor a shared data stream without knowing Marcus's dashboard depends on it; delays or interface changes can surface only when downstream work fails. | J65: Repeated pattern | K65: DI lacks dependency mapping, interface contracts and lightweight change communication for shared services. | L65: 5 | M65: High | N65: Extends Marcus's coordination issue from scheduling into technical dependency management.
B66: =IF(C66="","","OBS-"&TEXT(ROW()-2,"000")) -> OBS-064 | C66: Priya Sharma | D66: AI Investment Systems Pod | E66: 2026-09-18 | F66: ORG-01 | G66: Organization & Performance | H66: Accountability outside the pod defaults to the person most motivated to move the work forward. | I66: Vendor reviews, shared data problems and cross-pod commitments lack explicit ownership; expectations are often informal Slack promises, so tasks can be duplicated or missed. | J66: Repeated pattern | K66: Clear within-pod ownership is not matched by end-to-end accountability and escalation across DI and central functions. | L66: 5 | M66: High | N66: Further corroborates Elena and Marcus on cross-boundary accountability.
B67: =IF(C67="","","OBS-"&TEXT(ROW()-2,"000")) -> OBS-065 | C67: Priya Sharma | D67: AI Investment Systems Pod | E67: 2026-09-18 | F67: PLT-01 | G67: Shared Platform & Data Governance | H67: Shared infrastructure, DevOps and data-governance responsibilities fall between the pods. | I67: Neither pod clearly owns common cloud foundations, automated testing, shared documentation conventions or cross-pod data quality; teams may build separate cleanup solutions. | J67: Repeated pattern | K67: DI lacks explicit ownership and common standards for shared technical foundations used by multiple pods. | L67: 4 | M67: High | N67: New issue distinct from individual project dependencies; validate with architecture and support inventories.
... B71: =IF(C71="","","OBS-"&TEXT(ROW()-2,"000")) -> OBS-069 | C71: Priya Sharma | D71: AI Investment Systems Pod | E71: 2026-09-18 | F71: BVC-01 | G71: Business Case & Value Management | H71: DI does not consistently measure the impact of its investment systems. | I71: Priya reports that success is inferred largely from analyst satisfaction; she believes DI will need clearer outcome and ROI measures to justify increased headcount and budget. | J71: Perception / opinion | K71: DI lacks a practical measurement framework connecting delivered capabilities to user productivity, decision quality or other defensible outcomes. | L71: 4 | M71: Medium | N71: Corroborates James and Marcus; define metrics without overstating causal investment returns.
B72: =IF(C72="","","OBS-"&TEXT(ROW()-2,"000")) -> OBS-070 | C72: Priya Sharma | D72: AI Investment Systems Pod | E72: 2026-09-18 | G72: Strength / Context | H72: Priya considers formal career architecture and comprehensive documentation lower priority than intake and external bottlenecks over the next six months. | I72: Her team is small, senior and currently motivated by the work; she believes career frameworks can wait and documentation should improve after workload pressure is reduced. | J72: Perception / opinion | K72: People and knowledge issues may be real but are not equally urgent; prioritization should reflect current pain, scale timing and capacity to implement. | L72: 3 | M72: Medium | N72: Counter-evidence for urgency only; excluded from issue counts so it does not falsely increase corroboration.
B73: =IF(C73="","","OBS-"&TEXT(ROW()-2,"000")) -> OBS-071 | C73: Sarah | D73: Compliance / Central Function | E73: 2026-09-18 | G73: Strength / Context | H73: DI's leaders and engineers show respect for compliance obligations and collaborate constructively once engaged. | I73: Sarah described David as committed to doing things correctly and the engineers as patient, collaborative partners who explain technical details without dismissing Compliance. | J73: Perception / opinion | K73: The control model should build on a receptive culture rather than assume the team is intentionally disregarding regulatory obligations. | L73: 4 | M73: Medium | N73: Positive context only; excluded from issue counts and retained to define what the redesign should preserve.
B74: =IF(C74="","","OBS-"&TEXT(ROW()-2,"000")) -> OBS-072 | C74: Sarah | D74: Compliance / Central Function | E74: 2026-09-18 | F74: CORP-02 | G74: Corporate Interfaces | H74: Compliance is commonly engaged too late to influence project and data-source design efficiently. | I74: Sarah often learns about projects or vendors near launch; the physician-sentiment tool required last-minute privacy and vendor work that would have been easier during provider selection. | J74: Direct example | K74: DI lacks an early, reliable Compliance engagement point in its project lifecycle, creating avoidable rework and launch delay. | L74: 5 | M74: High | N74: Corroborates Marcus and Priya while clarifying that late visibility is a major cause of unpredictable review timelines.
B75: =IF(C75="","","OBS-"&TEXT(ROW()-2,"000")) -> OBS-073 | C75: Sarah | D75: Compliance / Central Function | E75: 2026-09-18 | F75: CORP-02 | G75: Corporate Interfaces | H75: The triggers for Compliance involvement are neither documented nor consistently understood. | I75: Engagement depends on David's intuition, email, Slack or an engineer realizing that Sarah may need to review a new data source, scraping method, model use or vendor contract. | J75: Repeated pattern | K75: DI lacks simple risk-based trigger questions and an intake mechanism that routes relevant work to Compliance at the appropriate stage. | L75: 5 | M75: High | N75: Same root cause as late engagement; do not treat the intake form itself as a separate issue.
B76: =IF(C76="","","OBS-"&TEXT(ROW()-2,"000")) -> OBS-074 | C76: Sarah | D76: Compliance / Central Function | E76: 2026-09-18 | F76: CORP-01 | G76: Corporate Interfaces | H76: New data vendors and AI services can be used before cross-functional due diligence is complete. | I76: Sarah discovered by chance that DI had integrated a data source with questionable sourcing practices; the team removed it after work had already been built on top of it. | J76: Direct example | K76: DI lacks a mandatory pre-use vendor and data-source gate that coordinates Procurement, Legal, Compliance and Security before commitment or integration. | L76: 5 | M76: High | N76: Strong corroboration of the procurement issue with evidence of rework and underlying regulatory exposure.
B77: =IF(C77="","","OBS-"&TEXT(ROW()-2,"000")) -> OBS-075 | C77: Sarah | D77: Compliance / Central Function | E77: 2026-09-18 | F77: CORP-01 | G77: Corporate Interfaces | H77: Vendor due diligence is not supported by a standard checklist, clear process owner or visible status. | I77: Sarah owns Compliance judgment but currently asks questions only after she becomes aware of a vendor; she wants Operations to ensure sourcing, privacy, contractual and security checks are completed. | J77: Repeated pattern | K77: The vendor pathway lacks standard submission requirements and end-to-end operational ownership, while specialist functions retain their decision rights. | L77: 5 | M77: High | N77: Corroborates Priya and James; Operations should own orchestration, not legal or compliance interpretation.
B78: =IF(C78="","","OBS-"&TEXT(ROW()-2,"000")) -> OBS-076 | C78: Sarah | D78: Compliance / Central Function | E78: 2026-09-18 | F78: CORP-01 | G78: Corporate Interfaces | H78: One-size-fits-all approval processes encourage DI to bypass controls for low-risk experimentation. | I78: Firm-wide software and procurement steps can take weeks even for a niche API or short experiment, so engineers sometimes work around the formal route to maintain speed. | J78: Repeated pattern | K78: DI needs a risk-tiered fast path that distinguishes sandbox experimentation from production use without creating an uncontrolled back door. | L78: 4 | M78: High | N78: Corroborates Elena, James and Priya on process fit; this is a design requirement within the procurement issue, not a separate policy issue.
B79: =IF(C79="","","OBS-"&TEXT(ROW()-2,"000")) -> OBS-077 | C79: Sarah | D79: Compliance / Central Function | E79: 2026-09-18 | F79: MDL-01 | G79: Model Governance | H79: DI lacks a formal inventory and governance lifecycle for AI models that influence investment activity. | I79: Sarah cannot point to a central record of model purpose, training data, limitations, bias, ownership, validation or ongoing performance and drift monitoring. | J79: Repeated pattern | K79: DI has not embedded minimum regulatory documentation, accountability and periodic review into the lifecycle of investment-related models. | L79: 5 | M79: High | N79: New issue distinct from general technical documentation because it governs regulated model use and evidence of control.
B80: =IF(C80="","","OBS-"&TEXT(ROW()-2,"000")) -> OBS-078 | C80: Sarah | D80: Compliance / Central Function | E80: 2026-09-18 | F80: MDL-01 | G80: Model Governance | H80: Technical model knowledge is not translated into evidence that can support regulatory review. | I80: Engineers focus on whether a model works, while Compliance needs to explain why it produced an outcome, how it was trained, its limitations and how behavior is monitored over time. | J80: Repeated pattern | K80: Model documentation is not part of the definition of done, leaving effective technical work without a defensible governance record. | L80: 5 | M80: High | N80: Same model-governance issue; Operations can enforce completion while technical owners provide content and Compliance sets standards.
B81: =IF(C81="","","OBS-"&TEXT(ROW()-2,"000")) -> OBS-079 | C81: Sarah | D81: Compliance / Central Function | E81: 2026-09-18 | F81: IAM-01 | G81: Access & Information Barriers | H81: Access controls and information barriers are not documented or evidenced at the level required for regulated investment activity. | I81: Sarah has repeatedly requested an access-control matrix and cannot definitively reconstruct who could access specific physician-sentiment data on a past date; policy is not consistently translated into engineering workflows. | J81: Direct example | K81: DI lacks documented access entitlements, review evidence and operational controls for sensitive research and data. | L81: 5 | M81: High | N81: New issue distinct from slow access provisioning: CORP-03 concerns enablement speed, while IAM-01 concerns control sufficiency and evidence.
B82: =IF(C82="","","OBS-"&TEXT(ROW()-2,"000")) -> OBS-080 | C82: Sarah | D82: Compliance / Central Function | E82: 2026-09-18 | F82: DPG-01 | G82: Data Privacy & Governance | H82: DI lacks a sufficiently explicit control framework for sensitive personal data and outbound third-party data use. | I82: Sarah highlighted PHI and PII exposure, missing data-flow diagrams and limited visibility into what sensitive information is sent to external AI tools or specialized APIs. | J82: Repeated pattern | K82: DI has not consistently documented data flows, permitted uses, external disclosures and required privacy protections for sensitive datasets. | L82: 5 | M82: High | N82: New issue focused on data handling after acquisition; vendor intake remains under CORP-01.
B83: =IF(C83="","","OBS-"&TEXT(ROW()-2,"000")) -> OBS-081 | C83: Sarah | D83: Compliance / Central Function | E83: 2026-09-18 | F83: PCE-02 | G83: Portfolio Company Engagement | H83: Regulatory responsibility and liability are unclear when DI deploys technology to portfolio companies. | I83: The team can treat a handoff as the portfolio company's responsibility, but Sarah believes accountability becomes ambiguous when DI supplies the technology, model or data. | J83: Perception / opinion | K83: DI lacks a standard risk and accountability framework for portfolio deployments, including ownership, permitted use, disclosures and escalation. | L83: 5 | M83: High | N83: New issue separate from PCE-01, which concerns engagement intake and counterpart obligations rather than regulatory accountability for deployed products.
B84: =IF(C84="","","OBS-"&TEXT(ROW()-2,"000")) -> OBS-082 | C84: Sarah | D84: Compliance / Central Function | E84: 2026-09-18 | F84: ORG-01 | G84: Organization & Performance | H84: Decision rights for data due diligence and live-model risk are unclear across DI and Compliance. | I84: Teams may assume an existing Deerfield vendor is approved for any use case, and ownership is unclear if a live model produces a biased or incorrect investment-relevant output. | J84: Repeated pattern | K84: DI has not defined who owns use-case approval, technical remediation, compliance assessment and escalation for live regulated systems. | L84: 5 | M84: High | N84: Corroborates the broader cross-boundary accountability issue with compliance-specific decision examples.
B85: =IF(C85="","","OBS-"&TEXT(ROW()-2,"000")) -> OBS-083 | C85: Sarah | D85: Compliance / Central Function | E85: 2026-09-18 | F85: ORG-01 | G85: Operating Model & Decision Rights | H85: The DI–Compliance relationship operates through ad hoc outreach rather than a predictable information-sharing cadence. | I85: There is no standing forum; Sarah pulls information from David and engineers and wants a bi-weekly roadmap preview with the Operations lead covering work moving from sandbox to production and new vendors. | J85: Repeated pattern | K85: DI lacks a named operational counterpart and recurring forum that provides central functions with timely roadmap context without consuming engineering capacity. | L85: 4 | M85: High | N85: Directly corroborates Priya's description of ad hoc central-function coordination.
B86: =IF(C86="","","OBS-"&TEXT(ROW()-2,"000")) -> OBS-084 | C86: Sarah | D86: Compliance / Central Function | E86: 2026-09-18 | F86: PLC-01 | G86: Product Lifecycle & Knowledge | H86: Compliance-relevant documentation is fragmented, unavailable or created only after request. | I86: Access lists, data-flow diagrams and high-level model records are not held in a central repository, leaving Sarah dependent on people remembering and reconstructing information. | J86: Repeated pattern | K86: DI lacks minimum documentation standards and a maintained source of truth for the operational and compliance record of products, models and data flows. | L86: 4 | M86: High | N86: Corroborates Marcus and Priya; more specialized control requirements remain captured under MDL-01, IAM-01 and DPG-01.
B87: =IF(C87="","","OBS-"&TEXT(ROW()-2,"000")) -> OBS-085 | C87: Sarah | D87: Compliance / Central Function | E87: 2026-09-18 | G87: Strength / Context | H87: Early-stage experimentation with public, non-sensitive data should remain lightweight. | I87: Sarah does not want lengthy review for sandbox exploration and estimates much routine checking could be handled through clear guardrails, reserving Compliance judgment for novel or high-risk uses. | J87: Perception / opinion | K87: The future control model should be risk-tiered, with explicit boundaries between experimentation and production and automated or checklist-based handling for routine cases. | L87: 4 | M87: High | N87: Design principle and counterweight to over-control; excluded from issue counts.
B88: =IF(C88="","","OBS-"&TEXT(ROW()-2,"000")) -> OBS-086 | C88: David Chen | D88: CIO / DI Leadership | E88: 2026-09-19 | G88: Strength / Context | H88: DI's speed, technical autonomy and ability to begin experiments quickly are central to its talent model and performance. | I88: David believes Priya and Marcus value the absence of large-company bureaucracy and wants product development and R&D to continue operating like a high-velocity technology team. | J88: Perception / opinion | K88: The operating model should add only the minimum structure needed for visibility, coordination and control while protecting technical autonomy and delivery speed. | L88: 5 | M88: High | N88: Leadership design principle; excluded from issue counts and retained to define what the redesign must preserve.
B89: =IF(C89="","","OBS-"&TEXT(ROW()-2,"000")) -> OBS-087 | C89: David Chen | D89: CIO / DI Leadership | E89: 2026-09-19 | G89: Strength / Context | H89: David wants DI to remain flat and avoid layers of middle management as it grows. | I89: He explicitly wants to preserve direct, rapid collaboration and avoid operational excellence becoming additional meetings, management layers or unused tracking requirements. | J89: Perception / opinion | K89: The target organization should first test whether clear pod leadership, decision rights and operating mechanisms can provide scale without a conventional management hierarchy. | L89: 4 | M89: High | N89: Counter-evidence to the urgency and form of WFP-02; excluded from issue counts rather than treated as additional corroboration.
B90: =IF(C90="","","OBS-"&TEXT(ROW()-2,"000")) -> OBS-088 | C90: David Chen | D90: CIO / DI Leadership | E90: 2026-09-19 | F90: PMO-01 | G90: Portfolio Visibility & Operating Rhythm | H90: David lacks a reliable source of truth for pod roadmaps, project status and budgets. | I90: He must find Marcus or Priya to understand current work; alignment lives largely in his head, the weekly sync is informal and there is no central dashboard or maintained roadmap. | J90: Repeated pattern | K90: DI lacks a lightweight portfolio view and operating rhythm that make priorities, status, dependencies and financial implications visible without manual inquiry. | L90: 5 | M90: High | N90: Strong leadership-level corroboration of the issue raised independently by both pod leads.
B91: =IF(C91="","","OBS-"&TEXT(ROW()-2,"000")) -> OBS-089 | C91: David Chen | D91: CIO / DI Leadership | E91: 2026-09-19 | F91: PIP-01 | G91: Portfolio Intake & Prioritization | H91: Resource conflicts and priority trade-offs depend on David's case-by-case intervention. | I91: When Priya and Marcus need the same technical capacity, both escalate to David; he decides based largely on immediate deadlines or financial importance and acknowledges the model will not scale. | J91: Repeated pattern | K91: DI lacks agreed prioritization criteria and a visible decision process that resolves trade-offs below the CIO level and makes displacement consequences explicit. | L91: 5 | M91: High | N91: Corroborates the pod interviews and identifies the current decision bottleneck directly.
B92: =IF(C92="","","OBS-"&TEXT(ROW()-2,"000")) -> OBS-090 | C92: David Chen | D92: CIO / DI Leadership | E92: 2026-09-19 | F92: ORG-01 | G92: Operating Model & Decision Rights | H92: David spends material time acting as the operational fixer and translator across corporate functions. | I92: He described chasing Finance on renewals, spending four hours translating a vendor contract and using personal political capital to accelerate HR, Legal and procurement matters. | J92: Direct example | K92: Missing operational ownership forces the CIO to manage routine exceptions and cross-functional translation instead of focusing on strategy, investment systems and organizational leadership. | L92: 5 | M92: High | N92: Extends the operational-leverage issue from pod leaders to the CIO.
B93: =IF(C93="","","OBS-"&TEXT(ROW()-2,"000")) -> OBS-091 | C93: David Chen | D93: CIO / DI Leadership | E93: 2026-09-19 | F93: ONB-01 | G93: Onboarding | H93: Access and compliance setup can prevent a new engineer from contributing code for approximately three weeks. | I93: David cited a recent engineer who lacked the required permissions for three weeks and set an aspiration for new engineers to become productive within four days. | J93: Direct example | K93: DI lacks an end-to-end, pre-coordinated technical onboarding pathway with clear owners and time-bound access provisioning. | L93: 5 | M93: High | N93: Appears to be the same incident cited by Elena and Priya; confirms leadership visibility but should not be counted as a third independent event.
B94: =IF(C94="","","OBS-"&TEXT(ROW()-2,"000")) -> OBS-092 | C94: David Chen | D94: CIO / DI Leadership | E94: 2026-09-19 | F94: VEN-01 | G94: Vendor & Contract Management | H94: DI lacks reliable oversight of vendor utilization and renewals. | I94: David discovered that DI had paid approximately $40,000 over six months for a SaaS tool that nobody was using and wants renewals visible before they occur. | J94: Direct example | K94: DI lacks a complete vendor inventory, accountable business owners, usage review and timely renewal decisions. | L94: 5 | M94: High | N94: Corroborates James's vendor-management evidence with a quantified example from the CIO; may refer to the same underlying portfolio review.
B95: =IF(C95="","","OBS-"&TEXT(ROW()-2,"000")) -> OBS-093 | C95: David Chen | D95: CIO / DI Leadership | E95: 2026-09-19 | F95: CORP-01 | G95: Corporate Interfaces | H95: The standard vendor and procurement pathway is disproportionate for low-dollar, time-sensitive technology purchases. | I95: David described lengthy negotiation for niche tools worth roughly $5,000–$10,000 and wants pre-approved templates and risk tiers so low-risk purchases move quickly. | J95: Repeated pattern | K95: DI needs a risk-tiered vendor pathway with standard terms, defined thresholds and escalation only for material exceptions. | L95: 5 | M95: High | N95: Strong corroboration of Elena, James, Priya and Sarah; fast-track design belongs within the procurement issue rather than becoming a separate issue.
B96: =IF(C96="","","OBS-"&TEXT(ROW()-2,"000")) -> OBS-094 | C96: David Chen | D96: CIO / DI Leadership | E96: 2026-09-19 | F96: CORP-02 | G96: Corporate Interfaces | H96: Legal and Compliance review of contracts and new data uses can be slow and overly bespoke relative to the underlying risk. | I96: David described multi-week contract redlining and repeated translation between technical vendors and corporate reviewers; data ingestion can require separate usage-rights and privacy discussions. | J96: Repeated pattern | K96: DI lacks a context-rich, risk-tiered Legal and Compliance workflow with standard positions, early engagement and clear escalation for true dealbreakers. | L96: 4 | M96: Medium | N96: Sarah corroborates the need for risk-tiering and early intake; validate exact Legal ownership because source descriptions of Sarah's functional role are inconsistent.
B97: =IF(C97="","","OBS-"&TEXT(ROW()-2,"000")) -> OBS-095 | C97: David Chen | D97: CIO / DI Leadership | E97: 2026-09-19 | F97: HIR-01 | G97: Hiring | H97: The current recruiting process is too slow to secure scarce senior technical talent. | I97: David cited a senior ML engineer search lasting four months, with candidates lost because feedback and decisions did not move at market speed. | J97: Direct example | K97: DI lacks an actively managed hiring process with reserved capacity, rapid feedback and clear ownership at each stage. | L97: 5 | M97: High | N97: Appears to be the same search cited by Elena; corroborates leadership concern but should not be counted as a separate hiring event.
B98: =IF(C98="","","OBS-"&TEXT(ROW()-2,"000")) -> OBS-096 | C98: David Chen | D98: CIO / DI Leadership | E98: 2026-09-19 | F98: ORG-01 | G98: Operating Model & Decision Rights | H98: DI lacks one operational interface across Finance, HR, Legal and Compliance. | I98: David currently translates technical urgency into corporate context himself and wants Operations to understand functional requirements, manage routine follow-through and escalate only the small number of genuine exceptions. | J98: Repeated pattern | K98: DI needs a single operational counterpart that preserves context across central functions while specialist teams retain their professional judgment and decision rights. | L98: 5 | M98: High | N98: Leadership-level corroboration of Priya and Sarah's central-function operating-model issue.
B99: =IF(C99="","","OBS-"&TEXT(ROW()-2,"000")) -> OBS-097 | C99: David Chen | D99: CIO / DI Leadership | E99: 2026-09-19 | F99: DPG-01 | G99: Data Privacy & Governance | H99: DI's high-velocity development model cannot extend unchanged to sensitive clinical data and regulated data use. | I99: David distinguishes fast experimentation in product development from the need to operate in lock-step with Deerfield on HIPAA, sensitive clinical data, intellectual-property rights and permitted data use. | J99: Perception / opinion | K99: DI lacks an explicit risk boundary that defines when experimentation becomes a governed data use requiring formal privacy, rights and control review. | L99: 5 | M99: High | N99: Corroborates Sarah's data-governance issue while establishing that the CIO supports stronger controls in this domain.
B100: =IF(C100="","","OBS-"&TEXT(ROW()-2,"000"))
B101: =IF(C101="","","OBS-"&TEXT(ROW()-2,"000"))
B102: =IF(C102="","","OBS-"&TEXT(ROW()-2,"000"))
B103: =IF(C103="","","OBS-"&TEXT(ROW()-2,"000"))
B104: =IF(C104="","","OBS-"&TEXT(ROW()-2,"000"))
B105: =IF(C105="","","OBS-"&TEXT(ROW()-2,"000"))
B106: =IF(C106="","","OBS-"&TEXT(ROW()-2,"000"))
B107: =IF(C107="","","OBS-"&TEXT(ROW()-2,"000"))
B108: =IF(C108="","","OBS-"&TEXT(ROW()-2,"000"))
B109: =IF(C109="","","OBS-"&TEXT(ROW()-2,"000"))
B110: =IF(C110="","","OBS-"&TEXT(ROW()-2,"000"))
...

Sheet 2_Issue Register
F2: Triangulate | K2: Prioritize | Q2: Sequencing
B3: Issue ID | C3: Issue / Gap Statement | D3: Category | E3: Root Cause Hypothesis | F3: Evidence Count | G3: Unique Sources* | H3: Strong Evidence Count | I3: Signal Strength | J3: Triangulation Confidence | K3: Business Impact (1-5) | L3: Urgency (1-5) | M3: Scale Dependency (1-5) | N3: Effort (1-5) | O3: Priority Score | P3: Priority Band | Q3: Dependency / Prerequisite | R3: Owner / Partner | S3: Readiness | T3: Suggested Sequence | U3: Final Sequence | V3: Proposed Intervention | W3: Target Outcome / Measure
B4: BVC-01 | C4: DI lacks full business-case visibility connecting material project spend to the outcomes created. | D4: Business Case & Value Management | E4: Material costs are not consistently attributed to workstreams, and success measures are not defined at intake or captured after delivery, preventing cost-to-outcome analysis. | F4: =IF(B4="","",COUNTIF('1_Evidence Log'!$F$3:$F$202,B4)) -> 4 | G4: =IF(B4="","",--(COUNTIFS('1_Evidence Log'!$F$3:$F$202,B4,'1_Evidence Log'!$C$3:$C$202,"Elena Rodriguez")>0)+--(COUNTIFS('1_Evidence Log'!$F$3:$F$202,B4,'1_Evidence Log'!$C$3:$C$202,"James Okonkwo")>0)+--(COUNTIFS('1_Evidence Log'!$F$3:$F$202,B4,'1_Evidence Log'!$C$3:$C$202,"Marcus Thompson")>0)+--(COUNTIFS('1_Evidence Log'!$F$3:$F$202,B4,'1_Evidence Log'!$C$3:$C$202,"Priya Sharma")>0)+--(COUNTIFS('1_Evidence Log'!$F$3:$F$202,B4,'1_Evidence Log'!$C$3:$C$202,"Sarah")>0)+--(COUNTIFS('1_Evidence Log'!$F$3:$F$202,B4,'1_Evidence Log'!$C$3:$C$202,"David Chen")>0)) -> 3 | H4: =IF(B4="","",COUNTIFS('1_Evidence Log'!$F$3:$F$202,B4,'1_Evidence Log'!$J$3:$J$202,"Direct example")+COUNTIFS('1_Evidence Log'!$F$3:$F$202,B4,'1_Evidence Log'!$J$3:$J$202,"Document / artifact")+COUNTIFS('1_Evidence Log'!$F$3:$F$202,B4,'1_Evidence Log'!$J$3:$J$202,"Observed behavior")+COUNTIFS('1_Evidence Log'!$F$3:$F$202,B4,'1_Evidence Log'!$J$3:$J$202,"Metric / data")) -> 0 | I4: =IF(B4="","",IF(AND(G4>=3,H4>=2),"Strong signal",IF(OR(G4>=2,H4>=1),"Emerging signal","Weak or unconfirmed"))) -> Emerging signal | J4: Medium | K4: 3 | L4: 3 | M4: 4 | N4: 4 | O4: =IF(COUNT(K4:N4)<4,"",ROUND((K4*0.35+L4*0.25+M4*0.25+(6-N4)*0.15)*20,0)) -> 62 | P4: =IF(O4="","",IF(O4>=80,"P1 — Critical",IF(O4>=65,"P2 — High",IF(O4>=50,"P3 — Medium","P4 — Longer-term")))) -> P3 — Medium | Q4: Requires stable project identifiers, material-cost tagging and credible outcome measures that avoid false precision or overstated investment causality. | R4: Director of Operations + Finance + pod leads + business sponsors | S4: Needs alignment | T4: =IF(P4="P1 — Critical","0–30 days",IF(P4="P2 — High","31–90 days","Post-90 days")) -> Post-90 days | U4: Post-90 days | V4: Add material cost ownership and expected outcome measures to intake, then review realized cost and outcomes at defined post-launch points. | W4: Material initiatives have an attributable cost, an accountable outcome owner and a defensible measure of value for prioritization and partner reporting.
B5: CAP-01 | C5: Capacity and delivery commitments are based on judgment rather than a visible workload view. | D5: Capacity Planning | E5: DI does not maintain a common view of committed work, available specialist capacity or the capacity effect of priority changes. | F5: =IF(B5="","",COUNTIF('1_Evidence Log'!$F$3:$F$202,B5)) -> 1 | G5: =IF(B5="","",--(COUNTIFS('1_Evidence Log'!$F$3:$F$202,B5,'1_Evidence Log'!$C$3:$C$202,"Elena Rodriguez")>0)+--(COUNTIFS('1_Evidence Log'!$F$3:$F$202,B5,'1_Evidence Log'!$C$3:$C$202,"James Okonkwo")>0)+--(COUNTIFS('1_Evidence Log'!$F$3:$F$202,B5,'1_Evidence Log'!$C$3:$C$202,"Marcus Thompson")>0)+--(COUNTIFS('1_Evidence Log'!$F$3:$F$202,B5,'1_Evidence Log'!$C$3:$C$202,"Priya Sharma")>0)+--(COUNTIFS('1_Evidence Log'!$F$3:$F$202,B5,'1_Evidence Log'!$C$3:$C$202,"Sarah")>0)+--(COUNTIFS('1_Evidence Log'!$F$3:$F$202,B5,'1_Evidence Log'!$C$3:$C$202,"David Chen")>0)) -> 1 | H5: =IF(B5="","",COUNTIFS('1_Evidence Log'!$F$3:$F$202,B5,'1_Evidence Log'!$J$3:$J$202,"Direct example")+COUNTIFS('1_Evidence Log'!$F$3:$F$202,B5,'1_Evidence Log'!$J$3:$J$202,"Document / artifact")+COUNTIFS('1_Evidence Log'!$F$3:$F$202,B5,'1_Evidence Log'!$J$3:$J$202,"Observed behavior")+COUNTIFS('1_Evidence Log'!$F$3:$F$202,B5,'1_Evidence Log'!$J$3:$J$202,"Metric / data")) -> 0 | I5: =IF(B5="","",IF(AND(G5>=3,H5>=2),"Strong signal",IF(OR(G5>=2,H5>=1),"Emerging signal","Weak or unconfirmed"))) -> Weak or unconfirmed | J5: Medium | K5: 5 | L5: 5 | M5: 5 | N5: 3 | O5: =IF(COUNT(K5:N5)<4,"",ROUND((K5*0.35+L5*0.25+M5*0.25+(6-N5)*0.15)*20,0)) -> 94 | P5: =IF(O5="","",IF(O5>=80,"P1 — Critical",IF(O5>=65,"P2 — High",IF(O5>=50,"P3 — Medium","P4 — Longer-term")))) -> P1 — Critical | Q5: Requires defined work categories and a deliberately lightweight approach that avoids detailed time tracking. | R5: Director of Operations + pod leads | S5: Needs alignment | T5: =IF(P5="P1 — Critical","0–30 days",IF(P5="P2 — High","31–90 days","Post-90 days")) -> 0–30 days | U5: 0–30 days | V5: Create a simple capacity view using team allocation bands, major commitments and known dependency demand. | W5: Pod leads can identify over-capacity roles and quantify the capacity displaced by a proposed priority change.
B6: CORP-01 | C6: Vendor and data-source onboarding lacks a fast, controlled end-to-end approval path. | D6: Corporate Interfaces | E6: Supplier intake has no single process owner, risk tiers, complete submission standard or visible stages, while the standard path is slow enough to encourage workarounds. | F6: =IF(B6="","",COUNTIF('1_Evidence Log'!$F$3:$F$202,B6)) -> 8 | G6: =IF(B6="","",--(COUNTIFS('1_Evidence Log'!$F$3:$F$202,B6,'1_Evidence Log'!$C$3:$C$202,"Elena Rodriguez")>0)+--(COUNTIFS('1_Evidence Log'!$F$3:$F$202,B6,'1_Evidence Log'!$C$3:$C$202,"James Okonkwo")>0)+--(COUNTIFS('1_Evidence Log'!$F$3:$F$202,B6,'1_Evidence Log'!$C$3:$C$202,"Marcus Thompson")>0)+--(COUNTIFS('1_Evidence Log'!$F$3:$F$202,B6,'1_Evidence Log'!$C$3:$C$202,"Priya Sharma")>0)+--(COUNTIFS('1_Evidence Log'!$F$3:$F$202,B6,'1_Evidence Log'!$C$3:$C$202,"Sarah")>0)+--(COUNTIFS('1_Evidence Log'!$F$3:$F$202,B6,'1_Evidence Log'!$C$3:$C$202,"David Chen")>0)) -> 5 | H6: =IF(B6="","",COUNTIFS('1_Evidence Log'!$F$3:$F$202,B6,'1_Evidence Log'!$J$3:$J$202,"Direct example")+COUNTIFS('1_Evidence Log'!$F$3:$F$202,B6,'1_Evidence Log'!$J$3:$J$202,"Document / artifact")+COUNTIFS('1_Evidence Log'!$F$3:$F$202,B6,'1_Evidence Log'!$J$3:$J$202,"Observed behavior")+COUNTIFS('1_Evidence Log'!$F$3:$F$202,B6,'1_Evidence Log'!$J$3:$J$202,"Metric / data")) -> 2 | I6: =IF(B6="","",IF(AND(G6>=3,H6>=2),"Strong signal",IF(OR(G6>=2,H6>=1),"Emerging signal","Weak or unconfirmed"))) -> Strong signal | J6: High | K6: 4 | L6: 4 | M6: 4 | N6: 3 | O6: =IF(COUNT(K6:N6)<4,"",ROUND((K6*0.35+L6*0.25+M6*0.25+(6-N6)*0.15)*20,0)) -> 77 | P6: =IF(O6="","",IF(O6>=80,"P1 — Critical",IF(O6>=65,"P2 — High",IF(O6>=50,"P3 — Medium","P4 — Longer-term")))) -> P2 — High | Q6: Scope is limited to supplier selection, diligence, contracting and pre-use approval; project and data-use review after acquisition sits under CORP-02. | R6: Director of Operations + Finance / Procurement + Legal / Compliance + Security | S6: Ready now | T6: =IF(P6="P1 — Critical","0–30 days",IF(P6="P2 — High","31–90 days","Post-90 days")) -> 31–90 days | U6: 31–60 days | V6: Create one risk-tiered intake, pre-approved paths for routine tools, standard due-diligence requirements, visible stages and service targets. | W6: All new vendors and data sources enter one workflow; routine requests follow a fast path and no tool reaches use before required reviews are complete.
B7: CORP-02 | C7: Projects, deployments and new data uses reach Legal and Compliance late and follow an opaque, overly bespoke review path. | D7: Legal & Compliance Workflow | E7: DI lacks lifecycle triggers, early roadmap visibility, standard submissions and risk-tiered review expectations for non-routine projects, deployments and data uses. | F7: =IF(B7="","",COUNTIF('1_Evidence Log'!$F$3:$F$202,B7)) -> 5 | G7: =IF(B7="","",--(COUNTIFS('1_Evidence Log'!$F$3:$F$202,B7,'1_Evidence Log'!$C$3:$C$202,"Elena Rodriguez")>0)+--(COUNTIFS('1_Evidence Log'!$F$3:$F$202,B7,'1_Evidence Log'!$C$3:$C$202,"James Okonkwo")>0)+--(COUNTIFS('1_Evidence Log'!$F$3:$F$202,B7,'1_Evidence Log'!$C$3:$C$202,"Marcus Thompson")>0)+--(COUNTIFS('1_Evidence Log'!$F$3:$F$202,B7,'1_Evidence Log'!$C$3:$C$202,"Priya Sharma")>0)+--(COUNTIFS('1_Evidence Log'!$F$3:$F$202,B7,'1_Evidence Log'!$C$3:$C$202,"Sarah")>0)+--(COUNTIFS('1_Evidence Log'!$F$3:$F$202,B7,'1_Evidence Log'!$C$3:$C$202,"David Chen")>0)) -> 4 | H7: =IF(B7="","",COUNTIFS('1_Evidence Log'!$F$3:$F$202,B7,'1_Evidence Log'!$J$3:$J$202,"Direct example")+COUNTIFS('1_Evidence Log'!$F$3:$F$202,B7,'1_Evidence Log'!$J$3:$J$202,"Document / artifact")+COUNTIFS('1_Evidence Log'!$F$3:$F$202,B7,'1_Evidence Log'!$J$3:$J$202,"Observed behavior")+COUNTIFS('1_Evidence Log'!$F$3:$F$202,B7,'1_Evidence Log'!$J$3:$J$202,"Metric / data")) -> 1 | I7: =IF(B7="","",IF(AND(G7>=3,H7>=2),"Strong signal",IF(OR(G7>=2,H7>=1),"Emerging signal","Weak or unconfirmed"))) -> Emerging signal | J7: High | K7: 4 | L7: 4 | M7: 4 | N7: 3 | O7: =IF(COUNT(K7:N7)<4,"",ROUND((K7*0.35+L7*0.25+M7*0.25+(6-N7)*0.15)*20,0)) -> 77 | P7: =IF(O7="","",IF(O7>=80,"P1 — Critical",IF(O7>=65,"P2 — High",IF(O7>=50,"P3 — Medium","P4 — Longer-term")))) -> P2 — High | Q7: Excludes supplier onboarding, which sits under CORP-01; requires confirmation of Legal versus Compliance authority and risk tiers. | R7: Director of Operations + Legal + Compliance | S7: Ready now | T7: =IF(P7="P1 — Critical","0–30 days",IF(P7="P2 — High","31–90 days","Post-90 days")) -> 31–90 days | U7: 61–90 days | V7: Embed simple risk triggers in project intake, provide standard submission templates and publish review stages and target turnaround by risk tier. | W7: Relevant work reaches reviewers during planning; DI can see status and expected timing, and routine reviews no longer require repeated translation.
B8: CORP-03 | C8: Ongoing security and data-access requests lack predictable routing, context and turnaround. | D8: Corporate Interfaces | E8: After hire onboarding, DI has no named technical interface or standard request path for project access, cloud permissions and portfolio-company enablement. | F8: =IF(B8="","",COUNTIF('1_Evidence Log'!$F$3:$F$202,B8)) -> 2 | G8: =IF(B8="","",--(COUNTIFS('1_Evidence Log'!$F$3:$F$202,B8,'1_Evidence Log'!$C$3:$C$202,"Elena Rodriguez")>0)+--(COUNTIFS('1_Evidence Log'!$F$3:$F$202,B8,'1_Evidence Log'!$C$3:$C$202,"James Okonkwo")>0)+--(COUNTIFS('1_Evidence Log'!$F$3:$F$202,B8,'1_Evidence Log'!$C$3:$C$202,"Marcus Thompson")>0)+--(COUNTIFS('1_Evidence Log'!$F$3:$F$202,B8,'1_Evidence Log'!$C$3:$C$202,"Priya Sharma")>0)+--(COUNTIFS('1_Evidence Log'!$F$3:$F$202,B8,'1_Evidence Log'!$C$3:$C$202,"Sarah")>0)+--(COUNTIFS('1_Evidence Log'!$F$3:$F$202,B8,'1_Evidence Log'!$C$3:$C$202,"David Chen")>0)) -> 2 | H8: =IF(B8="","",COUNTIFS('1_Evidence Log'!$F$3:$F$202,B8,'1_Evidence Log'!$J$3:$J$202,"Direct example")+COUNTIFS('1_Evidence Log'!$F$3:$F$202,B8,'1_Evidence Log'!$J$3:$J$202,"Document / artifact")+COUNTIFS('1_Evidence Log'!$F$3:$F$202,B8,'1_Evidence Log'!$J$3:$J$202,"Observed behavior")+COUNTIFS('1_Evidence Log'!$F$3:$F$202,B8,'1_Evidence Log'!$J$3:$J$202,"Metric / data")) -> 0 | I8: =IF(B8="","",IF(AND(G8>=3,H8>=2),"Strong signal",IF(OR(G8>=2,H8>=1),"Emerging signal","Weak or unconfirmed"))) -> Emerging signal | J8: High | K8: 4 | L8: 4 | M8: 4 | N8: 3 | O8: =IF(COUNT(K8:N8)<4,"",ROUND((K8*0.35+L8*0.25+M8*0.25+(6-N8)*0.15)*20,0)) -> 77 | P8: =IF(O8="","",IF(O8>=80,"P1 — Critical",IF(O8>=65,"P2 — High",IF(O8>=50,"P3 — Medium","P4 — Longer-term")))) -> P2 — High | Q8: Excludes new-hire provisioning, which sits under ONB-01; requires IT / SecOps capacity and separation of Deerfield versus portfolio-company steps. | R8: Director of Operations + IT / SecOps | S8: Needs alignment | T8: =IF(P8="P1 — Critical","0–30 days",IF(P8="P2 — High","31–90 days","Post-90 days")) -> 31–90 days | U8: 61–90 days | V8: Define request types, standard context, named escalation and service targets for common security and access needs. | W8: Common requests use a standard route with visible ownership and timing; baseline turnaround is measured and the largest delays have assigned fixes.
B9: DPG-01 | C9: DI lacks an explicit governance framework for sensitive data and outbound third-party data use. | D9: Data Privacy & Governance | E9: Data flows, permitted uses, external disclosures and privacy protections are not consistently documented as experiments move toward production. | F9: =IF(B9="","",COUNTIF('1_Evidence Log'!$F$3:$F$202,B9)) -> 2 | G9: =IF(B9="","",--(COUNTIFS('1_Evidence Log'!$F$3:$F$202,B9,'1_Evidence Log'!$C$3:$C$202,"Elena Rodriguez")>0)+--(COUNTIFS('1_Evidence Log'!$F$3:$F$202,B9,'1_Evidence Log'!$C$3:$C$202,"James Okonkwo")>0)+--(COUNTIFS('1_Evidence Log'!$F$3:$F$202,B9,'1_Evidence Log'!$C$3:$C$202,"Marcus Thompson")>0)+--(COUNTIFS('1_Evidence Log'!$F$3:$F$202,B9,'1_Evidence Log'!$C$3:$C$202,"Priya Sharma")>0)+--(COUNTIFS('1_Evidence Log'!$F$3:$F$202,B9,'1_Evidence Log'!$C$3:$C$202,"Sarah")>0)+--(COUNTIFS('1_Evidence Log'!$F$3:$F$202,B9,'1_Evidence Log'!$C$3:$C$202,"David Chen")>0)) -> 2 | H9: =IF(B9="","",COUNTIFS('1_Evidence Log'!$F$3:$F$202,B9,'1_Evidence Log'!$J$3:$J$202,"Direct example")+COUNTIFS('1_Evidence Log'!$F$3:$F$202,B9,'1_Evidence Log'!$J$3:$J$202,"Document / artifact")+COUNTIFS('1_Evidence Log'!$F$3:$F$202,B9,'1_Evidence Log'!$J$3:$J$202,"Observed behavior")+COUNTIFS('1_Evidence Log'!$F$3:$F$202,B9,'1_Evidence Log'!$J$3:$J$202,"Metric / data")) -> 0 | I9: =IF(B9="","",IF(AND(G9>=3,H9>=2),"Strong signal",IF(OR(G9>=2,H9>=1),"Emerging signal","Weak or unconfirmed"))) -> Emerging signal | J9: High | K9: 4 | L9: 4 | M9: 4 | N9: 3 | O9: =IF(COUNT(K9:N9)<4,"",ROUND((K9*0.35+L9*0.25+M9*0.25+(6-N9)*0.15)*20,0)) -> 77 | P9: =IF(O9="","",IF(O9>=80,"P1 — Critical",IF(O9>=65,"P2 — High",IF(O9>=50,"P3 — Medium","P4 — Longer-term")))) -> P2 — High | Q9: Requires data inventory, Compliance / Legal standards and alignment with vendor intake and model governance. | R9: Compliance / Legal + Priya + Director of Operations | S9: Needs alignment | T9: =IF(P9="P1 — Critical","0–30 days",IF(P9="P2 — High","31–90 days","Post-90 days")) -> 31–90 days | U9: Post-90 days | V9: Define data-risk tiers, sandbox-to-production triggers and minimum data-flow, rights and privacy documentation. | W9: Priority sensitive datasets have documented flows and permitted uses; new production uses cannot proceed without the required privacy and rights record.
B10: FIN-01 | C10: DI lacks a regular, driver-based financial planning process connecting roadmap, hiring, vendors and technology use to spend. | D10: Financial Planning & Spend Management | E10: Finance receives fragmented, exception-driven information because DI has no single owner for a rolling forecast and no regular mechanism to translate operating plans into financial implications. | F10: =IF(B10="","",COUNTIF('1_Evidence Log'!$F$3:$F$202,B10)) -> 6 | G10: =IF(B10="","",--(COUNTIFS('1_Evidence Log'!$F$3:$F$202,B10,'1_Evidence Log'!$C$3:$C$202,"Elena Rodriguez")>0)+--(COUNTIFS('1_Evidence Log'!$F$3:$F$202,B10,'1_Evidence Log'!$C$3:$C$202,"James Okonkwo")>0)+--(COUNTIFS('1_Evidence Log'!$F$3:$F$202,B10,'1_Evidence Log'!$C$3:$C$202,"Marcus Thompson")>0)+--(COUNTIFS('1_Evidence Log'!$F$3:$F$202,B10,'1_Evidence Log'!$C$3:$C$202,"Priya Sharma")>0)+--(COUNTIFS('1_Evidence Log'!$F$3:$F$202,B10,'1_Evidence Log'!$C$3:$C$202,"Sarah")>0)+--(COUNTIFS('1_Evidence Log'!$F$3:$F$202,B10,'1_Evidence Log'!$C$3:$C$202,"David Chen")>0)) -> 2 | H10: =IF(B10="","",COUNTIFS('1_Evidence Log'!$F$3:$F$202,B10,'1_Evidence Log'!$J$3:$J$202,"Direct example")+COUNTIFS('1_Evidence Log'!$F$3:$F$202,B10,'1_Evidence Log'!$J$3:$J$202,"Document / artifact")+COUNTIFS('1_Evidence Log'!$F$3:$F$202,B10,'1_Evidence Log'!$J$3:$J$202,"Observed behavior")+COUNTIFS('1_Evidence Log'!$F$3:$F$202,B10,'1_Evidence Log'!$J$3:$J$202,"Metric / data")) -> 2 | I10: =IF(B10="","",IF(AND(G10>=3,H10>=2),"Strong signal",IF(OR(G10>=2,H10>=1),"Emerging signal","Weak or unconfirmed"))) -> Emerging signal | J10: High | K10: 4 | L10: 4 | M10: 4 | N10: 3 | O10: =IF(COUNT(K10:N10)<4,"",ROUND((K10*0.35+L10*0.25+M10*0.25+(6-N10)*0.15)*20,0)) -> 77 | P10: =IF(O10="","",IF(O10>=80,"P1 — Critical",IF(O10>=65,"P2 — High",IF(O10>=50,"P3 — Medium","P4 — Longer-term")))) -> P2 — High | Q10: Depends on the initial portfolio view, workforce plan and vendor inventory; Finance remains the owner of firm-wide financial policy. | R10: Director of Operations + James / Finance + pod leads | S10: Needs alignment | T10: =IF(P10="P1 — Critical","0–30 days",IF(P10="P2 — High","31–90 days","Post-90 days")) -> 31–90 days | U10: 61–90 days | V10: Establish a monthly financial pulse and rolling six-month forecast linked to headcount, roadmap choices, cloud use and major vendor commitments. | W10: Finance receives 30–60 days' visibility on material changes; budget discussions use a common forecast rather than urgent invoices and retrospective explanations.
B11: FIN-02 | C11: Cloud spend is monitored too late to prevent material budget variance. | D11: Financial Planning & Spend Management | E11: Variable infrastructure consumption lacks weekly burn-rate visibility, anomaly alerts, thresholds and an accountable owner for investigation. | F11: =IF(B11="","",COUNTIF('1_Evidence Log'!$F$3:$F$202,B11)) -> 2 | G11: =IF(B11="","",--(COUNTIFS('1_Evidence Log'!$F$3:$F$202,B11,'1_Evidence Log'!$C$3:$C$202,"Elena Rodriguez")>0)+--(COUNTIFS('1_Evidence Log'!$F$3:$F$202,B11,'1_Evidence Log'!$C$3:$C$202,"James Okonkwo")>0)+--(COUNTIFS('1_Evidence Log'!$F$3:$F$202,B11,'1_Evidence Log'!$C$3:$C$202,"Marcus Thompson")>0)+--(COUNTIFS('1_Evidence Log'!$F$3:$F$202,B11,'1_Evidence Log'!$C$3:$C$202,"Priya Sharma")>0)+--(COUNTIFS('1_Evidence Log'!$F$3:$F$202,B11,'1_Evidence Log'!$C$3:$C$202,"Sarah")>0)+--(COUNTIFS('1_Evidence Log'!$F$3:$F$202,B11,'1_Evidence Log'!$C$3:$C$202,"David Chen")>0)) -> 1 | H11: =IF(B11="","",COUNTIFS('1_Evidence Log'!$F$3:$F$202,B11,'1_Evidence Log'!$J$3:$J$202,"Direct example")+COUNTIFS('1_Evidence Log'!$F$3:$F$202,B11,'1_Evidence Log'!$J$3:$J$202,"Document / artifact")+COUNTIFS('1_Evidence Log'!$F$3:$F$202,B11,'1_Evidence Log'!$J$3:$J$202,"Observed behavior")+COUNTIFS('1_Evidence Log'!$F$3:$F$202,B11,'1_Evidence Log'!$J$3:$J$202,"Metric / data")) -> 2 | I11: =IF(B11="","",IF(AND(G11>=3,H11>=2),"Strong signal",IF(OR(G11>=2,H11>=1),"Emerging signal","Weak or unconfirmed"))) -> Emerging signal | J11: Medium | K11: 4 | L11: 4 | M11: 4 | N11: 3 | O11: =IF(COUNT(K11:N11)<4,"",ROUND((K11*0.35+L11*0.25+M11*0.25+(6-N11)*0.15)*20,0)) -> 77 | P11: =IF(O11="","",IF(O11>=80,"P1 — Critical",IF(O11>=65,"P2 — High",IF(O11>=50,"P3 — Medium","P4 — Longer-term")))) -> P2 — High | Q11: Requires billing access, technical ownership and agreement on useful allocation and alert thresholds. | R11: Priya / platform owner + Director of Operations + Finance | S11: Ready now | T11: =IF(P11="P1 — Critical","0–30 days",IF(P11="P2 — High","31–90 days","Post-90 days")) -> 31–90 days | U11: 0–30 days | V11: Implement weekly cloud-cost reporting, anomaly alerts, tagged ownership and an escalation process for material variance. | W11: Cloud spend is visible during the month; material spikes trigger named follow-up within one business day and quarterly surprise variance is eliminated.
B12: HIR-01 | C12: The recruiting process is too slow and dependent on ad hoc coordination to support planned hiring volume. | D12: Hiring | E12: Once a role is approved, interview capacity is not reserved, stages run sequentially, feedback is delayed and final decisions depend heavily on David; role sequencing sits under WFP-01. | F12: =IF(B12="","",COUNTIF('1_Evidence Log'!$F$3:$F$202,B12)) -> 4 | G12: =IF(B12="","",--(COUNTIFS('1_Evidence Log'!$F$3:$F$202,B12,'1_Evidence Log'!$C$3:$C$202,"Elena Rodriguez")>0)+--(COUNTIFS('1_Evidence Log'!$F$3:$F$202,B12,'1_Evidence Log'!$C$3:$C$202,"James Okonkwo")>0)+--(COUNTIFS('1_Evidence Log'!$F$3:$F$202,B12,'1_Evidence Log'!$C$3:$C$202,"Marcus Thompson")>0)+--(COUNTIFS('1_Evidence Log'!$F$3:$F$202,B12,'1_Evidence Log'!$C$3:$C$202,"Priya Sharma")>0)+--(COUNTIFS('1_Evidence Log'!$F$3:$F$202,B12,'1_Evidence Log'!$C$3:$C$202,"Sarah")>0)+--(COUNTIFS('1_Evidence Log'!$F$3:$F$202,B12,'1_Evidence Log'!$C$3:$C$202,"David Chen")>0)) -> 2 | H12: =IF(B12="","",COUNTIFS('1_Evidence Log'!$F$3:$F$202,B12,'1_Evidence Log'!$J$3:$J$202,"Direct example")+COUNTIFS('1_Evidence Log'!$F$3:$F$202,B12,'1_Evidence Log'!$J$3:$J$202,"Document / artifact")+COUNTIFS('1_Evidence Log'!$F$3:$F$202,B12,'1_Evidence Log'!$J$3:$J$202,"Observed behavior")+COUNTIFS('1_Evidence Log'!$F$3:$F$202,B12,'1_Evidence Log'!$J$3:$J$202,"Metric / data")) -> 3 | I12: =IF(B12="","",IF(AND(G12>=3,H12>=2),"Strong signal",IF(OR(G12>=2,H12>=1),"Emerging signal","Weak or unconfirmed"))) -> Emerging signal | J12: High | K12: 5 | L12: 5 | M12: 5 | N12: 3 | O12: =IF(COUNT(K12:N12)<4,"",ROUND((K12*0.35+L12*0.25+M12*0.25+(6-N12)*0.15)*20,0)) -> 94 | P12: =IF(O12="","",IF(O12>=80,"P1 — Critical",IF(O12>=65,"P2 — High",IF(O12>=50,"P3 — Medium","P4 — Longer-term")))) -> P1 — Critical | Q12: Requires the workforce plan, clear assessment criteria and delegated decision rights by role level. | R12: Director of Operations + Elena / HR + hiring leads | S12: Ready now | T12: =IF(P12="P1 — Critical","0–30 days",IF(P12="P2 — High","31–90 days","Post-90 days")) -> 0–30 days | U12: 0–30 days | V12: Standardize requisition readiness, interview plans, reserved panels, parallel scheduling, feedback SLAs and decision authority. | W12: Every active search has a committed timeline and owner; scheduling and feedback occur within defined targets and time-to-hire begins to decline.
B13: HIR-02 | C13: Firm-wide office expectations may constrain access to specialized AI talent. | D13: Hiring | E13: DI has not defined when role scarcity and market practice justify location flexibility within Deerfield's workplace policy. | F13: =IF(B13="","",COUNTIF('1_Evidence Log'!$F$3:$F$202,B13)) -> 1 | G13: =IF(B13="","",--(COUNTIFS('1_Evidence Log'!$F$3:$F$202,B13,'1_Evidence Log'!$C$3:$C$202,"Elena Rodriguez")>0)+--(COUNTIFS('1_Evidence Log'!$F$3:$F$202,B13,'1_Evidence Log'!$C$3:$C$202,"James Okonkwo")>0)+--(COUNTIFS('1_Evidence Log'!$F$3:$F$202,B13,'1_Evidence Log'!$C$3:$C$202,"Marcus Thompson")>0)+--(COUNTIFS('1_Evidence Log'!$F$3:$F$202,B13,'1_Evidence Log'!$C$3:$C$202,"Priya Sharma")>0)+--(COUNTIFS('1_Evidence Log'!$F$3:$F$202,B13,'1_Evidence Log'!$C$3:$C$202,"Sarah")>0)+--(COUNTIFS('1_Evidence Log'!$F$3:$F$202,B13,'1_Evidence Log'!$C$3:$C$202,"David Chen")>0)) -> 1 | H13: =IF(B13="","",COUNTIFS('1_Evidence Log'!$F$3:$F$202,B13,'1_Evidence Log'!$J$3:$J$202,"Direct example")+COUNTIFS('1_Evidence Log'!$F$3:$F$202,B13,'1_Evidence Log'!$J$3:$J$202,"Document / artifact")+COUNTIFS('1_Evidence Log'!$F$3:$F$202,B13,'1_Evidence Log'!$J$3:$J$202,"Observed behavior")+COUNTIFS('1_Evidence Log'!$F$3:$F$202,B13,'1_Evidence Log'!$J$3:$J$202,"Metric / data")) -> 0 | I13: =IF(B13="","",IF(AND(G13>=3,H13>=2),"Strong signal",IF(OR(G13>=2,H13>=1),"Emerging signal","Weak or unconfirmed"))) -> Weak or unconfirmed | J13: Low | K13: 3 | L13: 2 | M13: 3 | N13: 5 | O13: =IF(COUNT(K13:N13)<4,"",ROUND((K13*0.35+L13*0.25+M13*0.25+(6-N13)*0.15)*20,0)) -> 49 | P13: =IF(O13="","",IF(O13>=80,"P1 — Critical",IF(O13>=65,"P2 — High",IF(O13>=50,"P3 — Medium","P4 — Longer-term")))) -> P4 — Longer-term | Q13: Requires evidence of candidate losses and a clear role-by-role talent-market case. | R13: David + Elena / HR + Director of Operations | S13: Needs alignment | T13: =IF(P13="P1 — Critical","0–30 days",IF(P13="P2 — High","31–90 days","Post-90 days")) -> Post-90 days | U13: Post-90 days | V13: Track location-related candidate losses and define an exception framework only if evidence supports it. | W13: DI has data on location constraints and an agreed decision rule; no policy exception is proposed without demonstrated recruiting impact.
B14: IAM-01 | C14: Access controls and information barriers are not documented or evidenced at the required level. | D14: Access & Information Barriers | E14: Policies are not consistently translated into system entitlements, periodic reviews and auditable records for sensitive research and data. | F14: =IF(B14="","",COUNTIF('1_Evidence Log'!$F$3:$F$202,B14)) -> 1 | G14: =IF(B14="","",--(COUNTIFS('1_Evidence Log'!$F$3:$F$202,B14,'1_Evidence Log'!$C$3:$C$202,"Elena Rodriguez")>0)+--(COUNTIFS('1_Evidence Log'!$F$3:$F$202,B14,'1_Evidence Log'!$C$3:$C$202,"James Okonkwo")>0)+--(COUNTIFS('1_Evidence Log'!$F$3:$F$202,B14,'1_Evidence Log'!$C$3:$C$202,"Marcus Thompson")>0)+--(COUNTIFS('1_Evidence Log'!$F$3:$F$202,B14,'1_Evidence Log'!$C$3:$C$202,"Priya Sharma")>0)+--(COUNTIFS('1_Evidence Log'!$F$3:$F$202,B14,'1_Evidence Log'!$C$3:$C$202,"Sarah")>0)+--(COUNTIFS('1_Evidence Log'!$F$3:$F$202,B14,'1_Evidence Log'!$C$3:$C$202,"David Chen")>0)) -> 1 | H14: =IF(B14="","",COUNTIFS('1_Evidence Log'!$F$3:$F$202,B14,'1_Evidence Log'!$J$3:$J$202,"Direct example")+COUNTIFS('1_Evidence Log'!$F$3:$F$202,B14,'1_Evidence Log'!$J$3:$J$202,"Document / artifact")+COUNTIFS('1_Evidence Log'!$F$3:$F$202,B14,'1_Evidence Log'!$J$3:$J$202,"Observed behavior")+COUNTIFS('1_Evidence Log'!$F$3:$F$202,B14,'1_Evidence Log'!$J$3:$J$202,"Metric / data")) -> 1 | I14: =IF(B14="","",IF(AND(G14>=3,H14>=2),"Strong signal",IF(OR(G14>=2,H14>=1),"Emerging signal","Weak or unconfirmed"))) -> Emerging signal | J14: Medium | K14: 4 | L14: 4 | M14: 4 | N14: 3 | O14: =IF(COUNT(K14:N14)<4,"",ROUND((K14*0.35+L14*0.25+M14*0.25+(6-N14)*0.15)*20,0)) -> 77 | P14: =IF(O14="","",IF(O14>=80,"P1 — Critical",IF(O14>=65,"P2 — High",IF(O14>=50,"P3 — Medium","P4 — Longer-term")))) -> P2 — High | Q14: Requires authoritative system and data inventories and ownership from IT / SecOps and Compliance. | R14: IT / SecOps + Compliance + Director of Operations | S14: Needs alignment | T14: =IF(P14="P1 — Critical","0–30 days",IF(P14="P2 — High","31–90 days","Post-90 days")) -> 31–90 days | U14: Post-90 days | V14: Create an access-control matrix for priority systems and data, assign review owners and establish evidence retention. | W14: DI can identify current access to high-risk systems and data and demonstrate review of those permissions; urgent exceptions are remediated.
B15: INT-01 | C15: DI is insufficiently integrated with the broader investment organization, weakening shared context and support for resources. | D15: DI-Deerfield Integration | E15: DI lacks deliberate stakeholder engagement and value communication beyond individual projects and requests. | F15: =IF(B15="","",COUNTIF('1_Evidence Log'!$F$3:$F$202,B15)) -> 1 | G15: =IF(B15="","",--(COUNTIFS('1_Evidence Log'!$F$3:$F$202,B15,'1_Evidence Log'!$C$3:$C$202,"Elena Rodriguez")>0)+--(COUNTIFS('1_Evidence Log'!$F$3:$F$202,B15,'1_Evidence Log'!$C$3:$C$202,"James Okonkwo")>0)+--(COUNTIFS('1_Evidence Log'!$F$3:$F$202,B15,'1_Evidence Log'!$C$3:$C$202,"Marcus Thompson")>0)+--(COUNTIFS('1_Evidence Log'!$F$3:$F$202,B15,'1_Evidence Log'!$C$3:$C$202,"Priya Sharma")>0)+--(COUNTIFS('1_Evidence Log'!$F$3:$F$202,B15,'1_Evidence Log'!$C$3:$C$202,"Sarah")>0)+--(COUNTIFS('1_Evidence Log'!$F$3:$F$202,B15,'1_Evidence Log'!$C$3:$C$202,"David Chen")>0)) -> 1 | H15: =IF(B15="","",COUNTIFS('1_Evidence Log'!$F$3:$F$202,B15,'1_Evidence Log'!$J$3:$J$202,"Direct example")+COUNTIFS('1_Evidence Log'!$F$3:$F$202,B15,'1_Evidence Log'!$J$3:$J$202,"Document / artifact")+COUNTIFS('1_Evidence Log'!$F$3:$F$202,B15,'1_Evidence Log'!$J$3:$J$202,"Observed behavior")+COUNTIFS('1_Evidence Log'!$F$3:$F$202,B15,'1_Evidence Log'!$J$3:$J$202,"Metric / data")) -> 0 | I15: =IF(B15="","",IF(AND(G15>=3,H15>=2),"Strong signal",IF(OR(G15>=2,H15>=1),"Emerging signal","Weak or unconfirmed"))) -> Weak or unconfirmed | J15: Low | K15: 3 | L15: 2 | M15: 3 | N15: 5 | O15: =IF(COUNT(K15:N15)<4,"",ROUND((K15*0.35+L15*0.25+M15*0.25+(6-N15)*0.15)*20,0)) -> 49 | P15: =IF(O15="","",IF(O15>=80,"P1 — Critical",IF(O15>=65,"P2 — High",IF(O15>=50,"P3 — Medium","P4 — Longer-term")))) -> P4 — Longer-term | Q15: Requires direct validation with Investment Partners and evidence that the perceived silo affects decisions or adoption. | R15: David + Director of Operations | S15: Needs alignment | T15: =IF(P15="P1 — Critical","0–30 days",IF(P15="P2 — High","31–90 days","Post-90 days")) -> Post-90 days | U15: Post-90 days | V15: Validate stakeholder needs and add targeted portfolio and value communication rather than a broad meeting layer. | W15: Within 90 days, partner interviews confirm whether this is a material issue and identify the smallest useful engagement mechanism.
... B34: XPD-01 | C34: Cross-pod dependencies are surfaced and committed too late, making delivery dates unreliable. | D34: Cross-Pod Coordination | E34: Pods maintain separate priorities and can make external commitments before shared capacity, interfaces and dependency dates are jointly accepted. | F34: =IF(B34="","",COUNTIF('1_Evidence Log'!$F$3:$F$202,B34)) -> 4 | G34: =IF(B34="","",--(COUNTIFS('1_Evidence Log'!$F$3:$F$202,B34,'1_Evidence Log'!$C$3:$C$202,"Elena Rodriguez")>0)+--(COUNTIFS('1_Evidence Log'!$F$3:$F$202,B34,'1_Evidence Log'!$C$3:$C$202,"James Okonkwo")>0)+--(COUNTIFS('1_Evidence Log'!$F$3:$F$202,B34,'1_Evidence Log'!$C$3:$C$202,"Marcus Thompson")>0)+--(COUNTIFS('1_Evidence Log'!$F$3:$F$202,B34,'1_Evidence Log'!$C$3:$C$202,"Priya Sharma")>0)+--(COUNTIFS('1_Evidence Log'!$F$3:$F$202,B34,'1_Evidence Log'!$C$3:$C$202,"Sarah")>0)+--(COUNTIFS('1_Evidence Log'!$F$3:$F$202,B34,'1_Evidence Log'!$C$3:$C$202,"David Chen")>0)) -> 2 | H34: =IF(B34="","",COUNTIFS('1_Evidence Log'!$F$3:$F$202,B34,'1_Evidence Log'!$J$3:$J$202,"Direct example")+COUNTIFS('1_Evidence Log'!$F$3:$F$202,B34,'1_Evidence Log'!$J$3:$J$202,"Document / artifact")+COUNTIFS('1_Evidence Log'!$F$3:$F$202,B34,'1_Evidence Log'!$J$3:$J$202,"Observed behavior")+COUNTIFS('1_Evidence Log'!$F$3:$F$202,B34,'1_Evidence Log'!$J$3:$J$202,"Metric / data")) -> 2 | I34: =IF(B34="","",IF(AND(G34>=3,H34>=2),"Strong signal",IF(OR(G34>=2,H34>=1),"Emerging signal","Weak or unconfirmed"))) -> Emerging signal | J34: High | K34: 5 | L34: 5 | M34: 5 | N34: 3 | O34: =IF(COUNT(K34:N34)<4,"",ROUND((K34*0.35+L34*0.25+M34*0.25+(6-N34)*0.15)*20,0)) -> 94 | P34: =IF(O34="","",IF(O34>=80,"P1 — Critical",IF(O34>=65,"P2 — High",IF(O34>=50,"P3 — Medium","P4 — Longer-term")))) -> P1 — Critical | Q34: Requires the shared portfolio view and explicit authority to accept cross-pod commitments. | R34: Director of Operations + Priya + Marcus | S34: Ready now | T34: =IF(P34="P1 — Critical","0–30 days",IF(P34="P2 — High","31–90 days","Post-90 days")) -> 0–30 days | U34: 0–30 days | V34: Add dependency mapping, joint acceptance and change notification to planning and project setup. | W34: Every cross-pod commitment has an accepted owner and date before an external promise is made; unresolved dependencies are reviewed weekly.
I35: =IF(B35="","",IF(AND(G35>=3,H35>=2),"Strong signal",IF(OR(G35>=2,H35>=1),"Emerging signal","Weak / unconfirmed"))) | O35: =IF(COUNT(K35:N35)<4,"",ROUND((K35*0.35+L35*0.25+M35*0.25+(6-N35)*0.15)*20,0))
I36: =IF(B36="","",IF(AND(G36>=3,H36>=2),"Strong signal",IF(OR(G36>=2,H36>=1),"Emerging signal","Weak / unconfirmed"))) | O36: =IF(COUNT(K36:N36)<4,"",ROUND((K36*0.35+L36*0.25+M36*0.25+(6-N36)*0.15)*20,0)) | T36: =IF(B36="","",IF(OR(I36="Weak / unconfirmed",J36="Low"),"Validate first",IF(S36="Blocked / dependency","Post-90 days",IF(O36>=80,"0–30 days",IF(O36>=65,"31–60 days",IF(O36>=50,"61–90 days","Monitor / no action"))))))
I37: =IF(B37="","",IF(AND(G37>=3,H37>=2),"Strong signal",IF(OR(G37>=2,H37>=1),"Emerging signal","Weak / unconfirmed"))) | O37: =IF(COUNT(K37:N37)<4,"",ROUND((K37*0.35+L37*0.25+M37*0.25+(6-N37)*0.15)*20,0)) | T37: =IF(B37="","",IF(OR(I37="Weak / unconfirmed",J37="Low"),"Validate first",IF(S37="Blocked / dependency","Post-90 days",IF(O37>=80,"0–30 days",IF(O37>=65,"31–60 days",IF(O37>=50,"61–90 days","Monitor / no action"))))))
I38: =IF(B38="","",IF(AND(G38>=3,H38>=2),"Strong signal",IF(OR(G38>=2,H38>=1),"Emerging signal","Weak / unconfirmed"))) | O38: =IF(COUNT(K38:N38)<4,"",ROUND((K38*0.35+L38*0.25+M38*0.25+(6-N38)*0.15)*20,0)) | T38: =IF(B38="","",IF(OR(I38="Weak / unconfirmed",J38="Low"),"Validate first",IF(S38="Blocked / dependency","Post-90 days",IF(O38>=80,"0–30 days",IF(O38>=65,"31–60 days",IF(O38>=50,"61–90 days","Monitor / no action"))))))
I39: =IF(B39="","",IF(AND(G39>=3,H39>=2),"Strong signal",IF(OR(G39>=2,H39>=1),"Emerging signal","Weak / unconfirmed"))) | O39: =IF(COUNT(K39:N39)<4,"",ROUND((K39*0.35+L39*0.25+M39*0.25+(6-N39)*0.15)*20,0)) | T39: =IF(B39="","",IF(OR(I39="Weak / unconfirmed",J39="Low"),"Validate first",IF(S39="Blocked / dependency","Post-90 days",IF(O39>=80,"0–30 days",IF(O39>=65,"31–60 days",IF(O39>=50,"61–90 days","Monitor / no action"))))))
I40: =IF(B40="","",IF(AND(G40>=3,H40>=2),"Strong signal",IF(OR(G40>=2,H40>=1),"Emerging signal","Weak / unconfirmed"))) | O40: =IF(COUNT(K40:N40)<4,"",ROUND((K40*0.35+L40*0.25+M40*0.25+(6-N40)*0.15)*20,0)) | T40: =IF(B40="","",IF(OR(I40="Weak / unconfirmed",J40="Low"),"Validate first",IF(S40="Blocked / dependency","Post-90 days",IF(O40>=80,"0–30 days",IF(O40>=65,"31–60 days",IF(O40>=50,"61–90 days","Monitor / no action"))))))
I41: =IF(B41="","",IF(AND(G41>=3,H41>=2),"Strong signal",IF(OR(G41>=2,H41>=1),"Emerging signal","Weak / unconfirmed"))) | O41: =IF(COUNT(K41:N41)<4,"",ROUND((K41*0.35+L41*0.25+M41*0.25+(6-N41)*0.15)*20,0)) | T41: =IF(B41="","",IF(OR(I41="Weak / unconfirmed",J41="Low"),"Validate first",IF(S41="Blocked / dependency","Post-90 days",IF(O41>=80,"0–30 days",IF(O41>=65,"31–60 days",IF(O41>=50,"61–90 days","Monitor / no action"))))))
I42: =IF(B42="","",IF(AND(G42>=3,H42>=2),"Strong signal",IF(OR(G42>=2,H42>=1),"Emerging signal","Weak / unconfirmed"))) | O42: =IF(COUNT(K42:N42)<4,"",ROUND((K42*0.35+L42*0.25+M42*0.25+(6-N42)*0.15)*20,0)) | T42: =IF(B42="","",IF(OR(I42="Weak / unconfirmed",J42="Low"),"Validate first",IF(S42="Blocked / dependency","Post-90 days",IF(O42>=80,"0–30 days",IF(O42>=65,"31–60 days",IF(O42>=50,"61–90 days","Monitor / no action"))))))
I43: =IF(B43="","",IF(AND(G43>=3,H43>=2),"Strong signal",IF(OR(G43>=2,H43>=1),"Emerging signal","Weak / unconfirmed"))) | O43: =IF(COUNT(K43:N43)<4,"",ROUND((K43*0.35+L43*0.25+M43*0.25+(6-N43)*0.15)*20,0)) | T43: =IF(B43="","",IF(OR(I43="Weak / unconfirmed",J43="Low"),"Validate first",IF(S43="Blocked / dependency","Post-90 days",IF(O43>=80,"0–30 days",IF(O43>=65,"31–60 days",IF(O43>=50,"61–90 days","Monitor / no action"))))))
I44: =IF(B44="","",IF(AND(G44>=3,H44>=2),"Strong signal",IF(OR(G44>=2,H44>=1),"Emerging signal","Weak / unconfirmed"))) | O44: =IF(COUNT(K44:N44)<4,"",ROUND((K44*0.35+L44*0.25+M44*0.25+(6-N44)*0.15)*20,0)) | T44: =IF(B44="","",IF(OR(I44="Weak / unconfirmed",J44="Low"),"Validate first",IF(S44="Blocked / dependency","Post-90 days",IF(O44>=80,"0–30 days",IF(O44>=65,"31–60 days",IF(O44>=50,"61–90 days","Monitor / no action"))))))
I45: =IF(B45="","",IF(AND(G45>=3,H45>=2),"Strong signal",IF(OR(G45>=2,H45>=1),"Emerging signal","Weak / unconfirmed"))) | O45: =IF(COUNT(K45:N45)<4,"",ROUND((K45*0.35+L45*0.25+M45*0.25+(6-N45)*0.15)*20,0)) | T45: =IF(B45="","",IF(OR(I45="Weak / unconfirmed",J45="Low"),"Validate first",IF(S45="Blocked / dependency","Post-90 days",IF(O45>=80,"0–30 days",IF(O45>=65,"31–60 days",IF(O45>=50,"61–90 days","Monitor / no action"))))))
I46: =IF(B46="","",IF(AND(G46>=3,H46>=2),"Strong signal",IF(OR(G46>=2,H46>=1),"Emerging signal","Weak / unconfirmed"))) | O46: =IF(COUNT(K46:N46)<4,"",ROUND((K46*0.35+L46*0.25+M46*0.25+(6-N46)*0.15)*20,0)) | T46: =IF(B46="","",IF(OR(I46="Weak / unconfirmed",J46="Low"),"Validate first",IF(S46="Blocked / dependency","Post-90 days",IF(O46>=80,"0–30 days",IF(O46>=65,"31–60 days",IF(O46>=50,"61–90 days","Monitor / no action"))))))
I47: =IF(B47="","",IF(AND(G47>=3,H47>=2),"Strong signal",IF(OR(G47>=2,H47>=1),"Emerging signal","Weak / unconfirmed"))) | O47: =IF(COUNT(K47:N47)<4,"",ROUND((K47*0.35+L47*0.25+M47*0.25+(6-N47)*0.15)*20,0)) | T47: =IF(B47="","",IF(OR(I47="Weak / unconfirmed",J47="Low"),"Validate first",IF(S47="Blocked / dependency","Post-90 days",IF(O47>=80,"0–30 days",IF(O47>=65,"31–60 days",IF(O47>=50,"61–90 days","Monitor / no action"))))))
... I103: =IF(B103="","",IF(AND(G103>=3,H103>=2),"Strong signal",IF(OR(G103>=2,H103>=1),"Emerging signal","Weak / unconfirmed"))) | O103: =IF(COUNT(K103:N103)<4,"",ROUND((K103*0.35+L103*0.25+M103*0.25+(6-N103)*0.15)*20,0)) | T103: =IF(B103="","",IF(OR(I103="Weak / unconfirmed",J103="Low"),"Validate first",IF(S103="Blocked / dependency","Post-90 days",IF(O103>=80,"0–30 days",IF(O103>=65,"31–60 days",IF(O103>=50,"61–90 days","Monitor / no action"))))))

Sheet 3_Sequence View
B2: Prioritized Sequencing View
B4: Issue ID | C4: Issue / Gap | D4: Signal | E4: Priority | F4: Score | G4: Final / Suggested Sequence | H4: Dependency | I4: Owner / Partner | J4: Intervention | K4: Outcome / Measure
B5: ='2_Issue Register'!B5 -> CAP-01 | C5: ='2_Issue Register'!C5 -> Capacity and delivery commitments are based on judgment rather than a visible workload view. | D5: ='2_Issue Register'!I5 -> Weak or unconfirmed | E5: ='2_Issue Register'!P5 -> P1 — Critical | F5: ='2_Issue Register'!O5 -> 94 | G5: =IF('2_Issue Register'!U5<>"",'2_Issue Register'!U5,'2_Issue Register'!T5) -> 0–30 days | H5: ='2_Issue Register'!Q5 -> Requires defined work categories and a deliberately lightweight approach that avoids detailed time tracking. | I5: ='2_Issue Register'!R5 -> Director of Operations + pod leads | J5: ='2_Issue Register'!V5 -> Create a simple capacity view using team allocation bands, major commitments and known dependency demand. | K5: ='2_Issue Register'!W5 -> Pod leads can identify over-capacity roles and quantify the capacity displaced by a proposed priority change.
B6: ='2_Issue Register'!B12 -> HIR-01 | C6: ='2_Issue Register'!C12 -> The recruiting process is too slow and dependent on ad hoc coordination to support planned hiring volume. | D6: ='2_Issue Register'!I12 -> Emerging signal | E6: ='2_Issue Register'!P12 -> P1 — Critical | F6: ='2_Issue Register'!O12 -> 94 | G6: =IF('2_Issue Register'!U12<>"",'2_Issue Register'!U12,'2_Issue Register'!T12) -> 0–30 days | H6: ='2_Issue Register'!Q12 -> Requires the workforce plan, clear assessment criteria and delegated decision rights by role level. | I6: ='2_Issue Register'!R12 -> Director of Operations + Elena / HR + hiring leads | J6: ='2_Issue Register'!V12 -> Standardize requisition readiness, interview plans, reserved panels, parallel scheduling, feedback SLAs and decision authority. | K6: ='2_Issue Register'!W12 -> Every active search has a committed timeline and owner; scheduling and feedback occur within defined targets and time-to-hire begins to decline.
B7: ='2_Issue Register'!B17 -> ONB-01 | C7: ='2_Issue Register'!C17 -> New-hire technical onboarding lacks an end-to-end owner, day-one access and a standard setup path. | D7: ='2_Issue Register'!I17 -> Strong signal | E7: ='2_Issue Register'!P17 -> P1 — Critical | F7: ='2_Issue Register'!O17 -> 94 | G7: =IF('2_Issue Register'!U17<>"",'2_Issue Register'!U17,'2_Issue Register'!T17) -> 0–30 days | H7: ='2_Issue Register'!Q17 -> Limited to pre-start and initial employee provisioning; ongoing project access sits under CORP-03. | I7: ='2_Issue Register'!R17 -> Director of Operations + IT / SecOps + hiring manager | J7: ='2_Issue Register'!V17 -> Create role-based access checklists, pre-start provisioning, a named onboarding owner and escalation targets. | K7: ='2_Issue Register'!W17 -> New engineers receive required baseline access by day one and can complete a defined productive engineering task within the first week.
B8: ='2_Issue Register'!B24 -> PIP-01 | C8: ='2_Issue Register'!C24 -> DI lacks a controlled intake and prioritization process across investment, portfolio-company and internal demand. | D8: ='2_Issue Register'!I24 -> Strong signal | E8: ='2_Issue Register'!P24 -> P1 — Critical | F8: ='2_Issue Register'!O24 -> 94 | G8: =IF('2_Issue Register'!U24<>"",'2_Issue Register'!U24,'2_Issue Register'!T24) -> 0–30 days | H8: ='2_Issue Register'!Q24 -> Requires agreement from David and pod leads on decision rights and prioritization criteria. | I8: ='2_Issue Register'!R24 -> Director of Operations + David + pod leads | J8: ='2_Issue Register'!V24 -> Create one intake, common evaluation criteria, a visible queue and a weekly prioritization decision forum. | K8: ='2_Issue Register'!W24 -> All new requests enter one queue; owners can identify accepted, deferred and displaced work and the reason for each decision.
B9: ='2_Issue Register'!B27 -> PMO-01 | C9: ='2_Issue Register'!C27 -> DI lacks a shared source of truth and forward-looking operating rhythm for its portfolio of work. | D9: ='2_Issue Register'!I27 -> Emerging signal | E9: ='2_Issue Register'!P27 -> P1 — Critical | F9: ='2_Issue Register'!O27 -> 94 | G9: =IF('2_Issue Register'!U27<>"",'2_Issue Register'!U27,'2_Issue Register'!T27) -> 0–30 days | H9: ='2_Issue Register'!Q27 -> Depends on minimum portfolio fields and update ownership; should launch with the intake process. | I9: ='2_Issue Register'!R27 -> Director of Operations + pod leads | J9: ='2_Issue Register'!V27 -> Stand up a lightweight portfolio view and redesign the weekly DI forum around decisions, dependencies, capacity and risks. | K9: ='2_Issue Register'!W27 -> One current portfolio view covers every active initiative; the weekly forum resolves exceptions rather than collecting status updates.
B10: ='2_Issue Register'!B34 -> XPD-01 | C10: ='2_Issue Register'!C34 -> Cross-pod dependencies are surfaced and committed too late, making delivery dates unreliable. | D10: ='2_Issue Register'!I34 -> Emerging signal | E10: ='2_Issue Register'!P34 -> P1 — Critical | F10: ='2_Issue Register'!O34 -> 94 | G10: =IF('2_Issue Register'!U34<>"",'2_Issue Register'!U34,'2_Issue Register'!T34) -> 0–30 days | H10: ='2_Issue Register'!Q34 -> Requires the shared portfolio view and explicit authority to accept cross-pod commitments. | I10: ='2_Issue Register'!R34 -> Director of Operations + Priya + Marcus | J10: ='2_Issue Register'!V34 -> Add dependency mapping, joint acceptance and change notification to planning and project setup. | K10: ='2_Issue Register'!W34 -> Every cross-pod commitment has an accepted owner and date before an external promise is made; unresolved dependencies are reviewed weekly.
B11: ='2_Issue Register'!B11 -> FIN-02 | C11: ='2_Issue Register'!C11 -> Cloud spend is monitored too late to prevent material budget variance. | D11: ='2_Issue Register'!I11 -> Emerging signal | E11: ='2_Issue Register'!P11 -> P2 — High | F11: ='2_Issue Register'!O11 -> 77 | G11: =IF('2_Issue Register'!U11<>"",'2_Issue Register'!U11,'2_Issue Register'!T11) -> 0–30 days | H11: ='2_Issue Register'!Q11 -> Requires billing access, technical ownership and agreement on useful allocation and alert thresholds. | I11: ='2_Issue Register'!R11 -> Priya / platform owner + Director of Operations + Finance | J11: ='2_Issue Register'!V11 -> Implement weekly cloud-cost reporting, anomaly alerts, tagged ownership and an escalation process for material variance. | K11: ='2_Issue Register'!W11 -> Cloud spend is visible during the month; material spikes trigger named follow-up within one business day and quarterly surprise variance is eliminated.
B12: ='2_Issue Register'!B18 -> ONB-02 | C12: ='2_Issue Register'!C18 -> New hires lack a structured first-30-day plan and integration into the broader firm. | D12: ='2_Issue Register'!I18 -> Weak or unconfirmed | E12: ='2_Issue Register'!P18 -> P2 — High | F12: ='2_Issue Register'!O18 -> 77 | G12: =IF('2_Issue Register'!U18<>"",'2_Issue Register'!U18,'2_Issue Register'!T18) -> 0–30 days | H12: ='2_Issue Register'!Q18 -> Should build on the technical-access checklist and requires hiring-manager ownership. | I12: ='2_Issue Register'!R18 -> Director of Operations + hiring managers + Elena / HR | J12: ='2_Issue Register'!V18 -> Create role-based 30-day plans, stakeholder maps, buddies and manager check-ins. | K12: ='2_Issue Register'!W18 -> Every new hire has documented first-month outcomes and key relationships; 30-day ramp feedback is collected and reviewed.
B13: ='2_Issue Register'!B29 -> VEN-01 | C13: ='2_Issue Register'!C29 -> DI lacks a complete vendor inventory, accountable owners and disciplined renewal management. | D13: ='2_Issue Register'!I29 -> Emerging signal | E13: ='2_Issue Register'!P29 -> P2 — High | F13: ='2_Issue Register'!O29 -> 77 | G13: =IF('2_Issue Register'!U29<>"",'2_Issue Register'!U29,'2_Issue Register'!T29) -> 0–30 days | H13: ='2_Issue Register'!Q29 -> Requires contract and payment data from Finance / Procurement and business-owner validation. | I13: ='2_Issue Register'!R29 -> Director of Operations + Finance / Procurement | J13: ='2_Issue Register'!V29 -> Complete a vendor and contract audit, centralize records, assign owners and institute 120/90/60-day renewal reviews. | K13: ='2_Issue Register'!W29 -> All active vendors have an owner, cost, usage status, contract location and renewal decision date; immediate duplicate and unused spend is addressed.
B14: ='2_Issue Register'!B6 -> CORP-01 | C14: ='2_Issue Register'!C6 -> Vendor and data-source onboarding lacks a fast, controlled end-to-end approval path. | D14: ='2_Issue Register'!I6 -> Strong signal | E14: ='2_Issue Register'!P6 -> P2 — High | F14: ='2_Issue Register'!O6 -> 77 | G14: =IF('2_Issue Register'!U6<>"",'2_Issue Register'!U6,'2_Issue Register'!T6) -> 31–60 days | H14: ='2_Issue Register'!Q6 -> Scope is limited to supplier selection, diligence, contracting and pre-use approval; project and data-use review after acquisition sits under CORP-02. | I14: ='2_Issue Register'!R6 -> Director of Operations + Finance / Procurement + Legal / Compliance + Security | J14: ='2_Issue Register'!V6 -> Create one risk-tiered intake, pre-approved paths for routine tools, standard due-diligence requirements, visible stages and service targets. | K14: ='2_Issue Register'!W6 -> All new vendors and data sources enter one workflow; routine requests follow a fast path and no tool reaches use before required reviews are complete.
B15: ='2_Issue Register'!B19 -> ORG-01 | C15: ='2_Issue Register'!C19 -> Recurring cross-boundary workflows lack explicit process owners, decision rights and escalation paths. | D15: ='2_Issue Register'!I19 -> Strong signal | E15: ='2_Issue Register'!P19 -> P2 — High | F15: ='2_Issue Register'!O19 -> 77 | G15: =IF('2_Issue Register'!U19<>"",'2_Issue Register'!U19,'2_Issue Register'!T19) -> 31–60 days | H15: ='2_Issue Register'!Q19 -> Requires David and functional leaders to agree which decisions Operations may make, coordinate or escalate. Process-specific gaps remain in their own issue rows. | I15: ='2_Issue Register'!R19 -> Director of Operations + David + functional leaders | J15: ='2_Issue Register'!V19 -> Define a decision-rights architecture and assign one operational owner for the highest-frequency cross-boundary workflows; keep specialist judgment with the relevant function. | K15: ='2_Issue Register'!W19 -> Priority workflows have one execution owner, explicit approvers and an escalation path; routine coordination no longer defaults to David or pod leaders.
B16: ='2_Issue Register'!B22 -> PCE-01 | C16: ='2_Issue Register'!C22 -> Portfolio-company engagements begin without a standardized handoff or clear counterpart responsibilities. | D16: ='2_Issue Register'!I22 -> Weak or unconfirmed | E16: ='2_Issue Register'!P22 -> P2 — High | F16: ='2_Issue Register'!O22 -> 77 | G16: =IF('2_Issue Register'!U22<>"",'2_Issue Register'!U22,'2_Issue Register'!T22) -> 31–60 days | H16: ='2_Issue Register'!Q22 -> Requires sponsor alignment and should be integrated into project intake and scoping. | I16: ='2_Issue Register'!R22 -> Director of Operations + Marcus + investment sponsor | J16: ='2_Issue Register'!V22 -> Create a portfolio-company engagement brief, sponsor checklist and mutual responsibility agreement. | K16: ='2_Issue Register'!W22 -> New engagements begin with a named sponsor and company counterpart, agreed problem statement, required inputs and escalation path.
B17: ='2_Issue Register'!B28 -> SCP-01 | C17: ='2_Issue Register'!C28 -> Accepted projects can begin without clear scope, stakeholder obligations or a definition of done. | D17: ='2_Issue Register'!I28 -> Emerging signal | E17: ='2_Issue Register'!P28 -> P2 — High | F17: ='2_Issue Register'!O28 -> 77 | G17: =IF('2_Issue Register'!U28<>"",'2_Issue Register'!U28,'2_Issue Register'!T28) -> 31–60 days | H17: ='2_Issue Register'!Q28 -> Should align with the portfolio-company engagement model and intake gate. | I17: ='2_Issue Register'!R28 -> Director of Operations + Marcus | J17: ='2_Issue Register'!V28 -> Introduce a one-page engagement charter and stage gates for material projects. | K17: ='2_Issue Register'!W28 -> All newly accepted material projects document scope, sponsor, inputs, milestones, definition of done and transition approach before work begins.
B18: ='2_Issue Register'!B30 -> WFP-01 | C18: ='2_Issue Register'!C30 -> DI lacks a clear, sequenced workforce plan for growth from 10 to 30. | D18: ='2_Issue Register'!I30 -> Weak or unconfirmed | E18: ='2_Issue Register'!P30 -> P2 — High | F18: ='2_Issue Register'!O30 -> 77 | G18: =IF('2_Issue Register'!U30<>"",'2_Issue Register'!U30,'2_Issue Register'!T30) -> 31–60 days | H18: ='2_Issue Register'!Q30 -> Depends on strategy, portfolio priorities, capacity baseline and target organization choices. | I18: ='2_Issue Register'!R30 -> David + Director of Operations + Elena / HR + pod leads | J18: ='2_Issue Register'!V30 -> Create an 18-month role and capability plan with hiring sequence, triggers, cost and dependencies. | K18: ='2_Issue Register'!W30 -> Each planned role has a business rationale, timing trigger, reporting line and budget; recruiting begins from an agreed sequence rather than immediate pressure.
B19: ='2_Issue Register'!B7 -> CORP-02 | C19: ='2_Issue Register'!C7 -> Projects, deployments and new data uses reach Legal and Compliance late and follow an opaque, overly bespoke review path. | D19: ='2_Issue Register'!I7 -> Emerging signal | E19: ='2_Issue Register'!P7 -> P2 — High | F19: ='2_Issue Register'!O7 -> 77 | G19: =IF('2_Issue Register'!U7<>"",'2_Issue Register'!U7,'2_Issue Register'!T7) -> 61–90 days | H19: ='2_Issue Register'!Q7 -> Excludes supplier onboarding, which sits under CORP-01; requires confirmation of Legal versus Compliance authority and risk tiers. | I19: ='2_Issue Register'!R7 -> Director of Operations + Legal + Compliance | J19: ='2_Issue Register'!V7 -> Embed simple risk triggers in project intake, provide standard submission templates and publish review stages and target turnaround by risk tier. | K19: ='2_Issue Register'!W7 -> Relevant work reaches reviewers during planning; DI can see status and expected timing, and routine reviews no longer require repeated translation.
B20: ='2_Issue Register'!B8 -> CORP-03 | C20: ='2_Issue Register'!C8 -> Ongoing security and data-access requests lack predictable routing, context and turnaround. | D20: ='2_Issue Register'!I8 -> Emerging signal | E20: ='2_Issue Register'!P8 -> P2 — High | F20: ='2_Issue Register'!O8 -> 77 | G20: =IF('2_Issue Register'!U8<>"",'2_Issue Register'!U8,'2_Issue Register'!T8) -> 61–90 days | H20: ='2_Issue Register'!Q8 -> Excludes new-hire provisioning, which sits under ONB-01; requires IT / SecOps capacity and separation of Deerfield versus portfolio-company steps. | I20: ='2_Issue Register'!R8 -> Director of Operations + IT / SecOps | J20: ='2_Issue Register'!V8 -> Define request types, standard context, named escalation and service targets for common security and access needs. | K20: ='2_Issue Register'!W8 -> Common requests use a standard route with visible ownership and timing; baseline turnaround is measured and the largest delays have assigned fixes.
B21: ='2_Issue Register'!B10 -> FIN-01 | C21: ='2_Issue Register'!C10 -> DI lacks a regular, driver-based financial planning process connecting roadmap, hiring, vendors and technology use to spend. | D21: ='2_Issue Register'!I10 -> Emerging signal | E21: ='2_Issue Register'!P10 -> P2 — High | F21: ='2_Issue Register'!O10 -> 77 | G21: =IF('2_Issue Register'!U10<>"",'2_Issue Register'!U10,'2_Issue Register'!T10) -> 61–90 days | H21: ='2_Issue Register'!Q10 -> Depends on the initial portfolio view, workforce plan and vendor inventory; Finance remains the owner of firm-wide financial policy. | I21: ='2_Issue Register'!R10 -> Director of Operations + James / Finance + pod leads | J21: ='2_Issue Register'!V10 -> Establish a monthly financial pulse and rolling six-month forecast linked to headcount, roadmap choices, cloud use and major vendor commitments. | K21: ='2_Issue Register'!W10 -> Finance receives 30–60 days' visibility on material changes; budget discussions use a common forecast rather than urgent invoices and retrospective explanations.
B22: ='2_Issue Register'!B9 -> DPG-01 | C22: ='2_Issue Register'!C9 -> DI lacks an explicit governance framework for sensitive data and outbound third-party data use. | D22: ='2_Issue Register'!I9 -> Emerging signal | E22: ='2_Issue Register'!P9 -> P2 — High | F22: ='2_Issue Register'!O9 -> 77 | G22: =IF('2_Issue Register'!U9<>"",'2_Issue Register'!U9,'2_Issue Register'!T9) -> Post-90 days | H22: ='2_Issue Register'!Q9 -> Requires data inventory, Compliance / Legal standards and alignment with vendor intake and model governance. | I22: ='2_Issue Register'!R9 -> Compliance / Legal + Priya + Director of Operations | J22: ='2_Issue Register'!V9 -> Define data-risk tiers, sandbox-to-production triggers and minimum data-flow, rights and privacy documentation. | K22: ='2_Issue Register'!W9 -> Priority sensitive datasets have documented flows and permitted uses; new production uses cannot proceed without the required privacy and rights record.
B23: ='2_Issue Register'!B14 -> IAM-01 | C23: ='2_Issue Register'!C14 -> Access controls and information barriers are not documented or evidenced at the required level. | D23: ='2_Issue Register'!I14 -> Emerging signal | E23: ='2_Issue Register'!P14 -> P2 — High | F23: ='2_Issue Register'!O14 -> 77 | G23: =IF('2_Issue Register'!U14<>"",'2_Issue Register'!U14,'2_Issue Register'!T14) -> Post-90 days | H23: ='2_Issue Register'!Q14 -> Requires authoritative system and data inventories and ownership from IT / SecOps and Compliance. | I23: ='2_Issue Register'!R14 -> IT / SecOps + Compliance + Director of Operations | J23: ='2_Issue Register'!V14 -> Create an access-control matrix for priority systems and data, assign review owners and establish evidence retention. | K23: ='2_Issue Register'!W14 -> DI can identify current access to high-risk systems and data and demonstrate review of those permissions; urgent exceptions are remediated.
B24: ='2_Issue Register'!B23 -> PCE-02 | C24: ='2_Issue Register'!C23 -> Regulatory responsibility and liability are unclear when DI deploys technology to portfolio companies. | D24: ='2_Issue Register'!I23 -> Weak or unconfirmed | E24: ='2_Issue Register'!P23 -> P2 — High | F24: ='2_Issue Register'!O23 -> 77 | G24: =IF('2_Issue Register'!U23<>"",'2_Issue Register'!U23,'2_Issue Register'!T23) -> Post-90 days | H24: ='2_Issue Register'!Q23 -> Requires Legal and Compliance policy decisions and an inventory of current deployments. | I24: ='2_Issue Register'!R23 -> Compliance / Legal + Director of Operations + Marcus | J24: ='2_Issue Register'!V23 -> Define a risk and accountability framework for portfolio deployments, with standard terms and review triggers. | K24: ='2_Issue Register'!W23 -> Every active deployment has documented accountability, permitted use, data responsibilities and an escalation owner; new deployments use the standard framework.
B25: ='2_Issue Register'!B4 -> BVC-01 | C25: ='2_Issue Register'!C4 -> DI lacks full business-case visibility connecting material project spend to the outcomes created. | D25: ='2_Issue Register'!I4 -> Emerging signal | E25: ='2_Issue Register'!P4 -> P3 — Medium | F25: ='2_Issue Register'!O4 -> 62 | G25: =IF('2_Issue Register'!U4<>"",'2_Issue Register'!U4,'2_Issue Register'!T4) -> Post-90 days | H25: ='2_Issue Register'!Q4 -> Requires stable project identifiers, material-cost tagging and credible outcome measures that avoid false precision or overstated investment causality. | I25: ='2_Issue Register'!R4 -> Director of Operations + Finance + pod leads + business sponsors | J25: ='2_Issue Register'!V4 -> Add material cost ownership and expected outcome measures to intake, then review realized cost and outcomes at defined post-launch points. | K25: ='2_Issue Register'!W4 -> Material initiatives have an attributable cost, an accountable outcome owner and a defensible measure of value for prioritization and partner reporting.
B26: ='2_Issue Register'!B16 -> MDL-01 | C26: ='2_Issue Register'!C16 -> DI lacks a formal inventory and governance lifecycle for AI models used in investment activity. | D26: ='2_Issue Register'!I16 -> Weak or unconfirmed | E26: ='2_Issue Register'!P16 -> P3 — Medium | F26: ='2_Issue Register'!O16 -> 62 | G26: =IF('2_Issue Register'!U16<>"",'2_Issue Register'!U16,'2_Issue Register'!T16) -> Post-90 days | H26: ='2_Issue Register'!Q16 -> Requires Compliance standards, technical-owner input and scoping to investment-relevant production models first. | I26: ='2_Issue Register'!R16 -> Compliance + Priya / model owners + Director of Operations | J26: ='2_Issue Register'!V16 -> Create a model inventory, minimum model record, accountable owners and risk-based validation and monitoring cadence. | K26: ='2_Issue Register'!W16 -> All production investment-related models are inventoried with owner, purpose, data, limitations and review status; highest-risk gaps have remediation plans.
B27: ='2_Issue Register'!B25 -> PLC-01 | C27: ='2_Issue Register'!C25 -> Post-launch ownership, support expectations and critical product knowledge are not consistently maintained. | D27: ='2_Issue Register'!I25 -> Emerging signal | E27: ='2_Issue Register'!P25 -> P3 — Medium | F27: ='2_Issue Register'!O25 -> 62 | G27: =IF('2_Issue Register'!U25<>"",'2_Issue Register'!U25,'2_Issue Register'!T25) -> Post-90 days | H27: ='2_Issue Register'!Q25 -> Requires a current inventory of deployed products and protected technical-owner time. | I27: ='2_Issue Register'!R25 -> Director of Operations + technical product owners | J27: ='2_Issue Register'!V25 -> Create a product inventory, assign lifecycle owners and set proportional documentation and support standards. | K27: ='2_Issue Register'!W25 -> Every production tool has an owner, support model and current core documentation; orphaned or obsolete products are identified.
B28: ='2_Issue Register'!B26 -> PLT-01 | C28: ='2_Issue Register'!C26 -> Ownership and standards for shared infrastructure, DevOps and cross-pod data foundations are unclear. | D28: ='2_Issue Register'!I26 -> Weak or unconfirmed | E28: ='2_Issue Register'!P26 -> P3 — Medium | F28: ='2_Issue Register'!O26 -> 62 | G28: =IF('2_Issue Register'!U26<>"",'2_Issue Register'!U26,'2_Issue Register'!T26) -> Post-90 days | H28: ='2_Issue Register'!Q26 -> Requires a technical architecture and responsibility review with both pods. | I28: ='2_Issue Register'!R26 -> Priya + designated platform owner + Director of Operations | J28: ='2_Issue Register'!V26 -> Map shared services, assign technical owners and define minimum standards for interfaces, testing and data quality. | K28: ='2_Issue Register'!W26 -> Critical shared services have named owners, service expectations and change controls; duplicate or unmanaged foundations are identified.
B29: ='2_Issue Register'!B31 -> WFP-02 | C29: ='2_Issue Register'!C31 -> DI has not resolved how leadership structure and management capacity should evolve as the team grows. | D29: ='2_Issue Register'!I31 -> Weak or unconfirmed | E29: ='2_Issue Register'!P31 -> P3 — Medium | F29: ='2_Issue Register'!O31 -> 62 | G29: =IF('2_Issue Register'!U31<>"",'2_Issue Register'!U31,'2_Issue Register'!T31) -> Post-90 days | H29: ='2_Issue Register'!Q31 -> Requires target-organization design and explicit consideration of David's preference to preserve a flat structure. | I29: ='2_Issue Register'!R31 -> David + Director of Operations + Elena / HR | J29: ='2_Issue Register'!V31 -> Design and test target spans, pod-lead accountabilities and decision delegation before adding management layers. | K29: ='2_Issue Register'!W31 -> DI has an agreed target organization for 15, 20 and 30 people, with trigger points for new leadership roles and clear delegated decisions.
B30: ='2_Issue Register'!B13 -> HIR-02 | C30: ='2_Issue Register'!C13 -> Firm-wide office expectations may constrain access to specialized AI talent. | D30: ='2_Issue Register'!I13 -> Weak or unconfirmed | E30: ='2_Issue Register'!P13 -> P4 — Longer-term | F30: ='2_Issue Register'!O13 -> 49 | G30: =IF('2_Issue Register'!U13<>"",'2_Issue Register'!U13,'2_Issue Register'!T13) -> Post-90 days | H30: ='2_Issue Register'!Q13 -> Requires evidence of candidate losses and a clear role-by-role talent-market case. | I30: ='2_Issue Register'!R13 -> David + Elena / HR + Director of Operations | J30: ='2_Issue Register'!V13 -> Track location-related candidate losses and define an exception framework only if evidence supports it. | K30: ='2_Issue Register'!W13 -> DI has data on location constraints and an agreed decision rule; no policy exception is proposed without demonstrated recruiting impact.
B31: ='2_Issue Register'!B15 -> INT-01 | C31: ='2_Issue Register'!C15 -> DI is insufficiently integrated with the broader investment organization, weakening shared context and support for resources. | D31: ='2_Issue Register'!I15 -> Weak or unconfirmed | E31: ='2_Issue Register'!P15 -> P4 — Longer-term | F31: ='2_Issue Register'!O15 -> 49 | G31: =IF('2_Issue Register'!U15<>"",'2_Issue Register'!U15,'2_Issue Register'!T15) -> Post-90 days | H31: ='2_Issue Register'!Q15 -> Requires direct validation with Investment Partners and evidence that the perceived silo affects decisions or adoption. | I31: ='2_Issue Register'!R15 -> David + Director of Operations | J31: ='2_Issue Register'!V15 -> Validate stakeholder needs and add targeted portfolio and value communication rather than a broad meeting layer. | K31: ='2_Issue Register'!W15 -> Within 90 days, partner interviews confirm whether this is a material issue and identify the smallest useful engagement mechanism.
B32: ='2_Issue Register'!B20 -> ORG-02 | C32: ='2_Issue Register'!C20 -> Performance management is informal and insufficiently documented. | D32: ='2_Issue Register'!I20 -> Weak or unconfirmed | E32: ='2_Issue Register'!P20 -> P4 — Longer-term | F32: ='2_Issue Register'!O20 -> 49 | G32: =IF('2_Issue Register'!U20<>"",'2_Issue Register'!U20,'2_Issue Register'!T20) -> Post-90 days | H32: ='2_Issue Register'!Q20 -> Requires clarified role expectations and HR agreement on minimum documentation. | I32: ='2_Issue Register'!R20 -> David + pod leads + Elena / HR | J32: ='2_Issue Register'!V20 -> Define quarterly expectation and feedback check-ins with minimum documentation tied to the annual process. | K32: ='2_Issue Register'!W20 -> All employees have current expectations and documented feedback; year-end decisions no longer rely only on memory and visibility.
B33: ='2_Issue Register'!B21 -> ORG-03 | C33: ='2_Issue Register'!C21 -> Annual compensation cycles do not provide a clear response path for time-sensitive retention risks. | D33: ='2_Issue Register'!I21 -> Weak or unconfirmed | E33: ='2_Issue Register'!P21 -> P4 — Longer-term | F33: ='2_Issue Register'!O21 -> 49 | G33: =IF('2_Issue Register'!U21<>"",'2_Issue Register'!U21,'2_Issue Register'!T21) -> Post-90 days | H33: ='2_Issue Register'!Q21 -> Requires Compensation Committee policy and evidence on the frequency and impact of retention exceptions. | I33: ='2_Issue Register'!R21 -> Elena / HR + David + Compensation Committee | J33: ='2_Issue Register'!V21 -> Define a documented escalation and evidence standard for exceptional retention cases. | K33: ='2_Issue Register'!W21 -> DI and HR know when and how an out-of-cycle case can be raised, with explicit decision authority and turnaround expectations.
B34: ='2_Issue Register'!B32 -> WFP-03 | C34: ='2_Issue Register'!C32 -> Levels and career paths are not defined for DI technical talent. | D34: ='2_Issue Register'!I32 -> Weak or unconfirmed | E34: ='2_Issue Register'!P32 -> P4 — Longer-term | F34: ='2_Issue Register'!O32 -> 49 | G34: =IF('2_Issue Register'!U32<>"",'2_Issue Register'!U32,'2_Issue Register'!T32) -> Post-90 days | H34: ='2_Issue Register'!Q32 -> Should follow the target organization and job-architecture work; current employees have not identified it as an immediate pain point. | I34: ='2_Issue Register'!R32 -> Elena / HR + pod leads + Director of Operations | J34: ='2_Issue Register'!V32 -> Define a lightweight technical career framework once the target organization and role architecture are settled. | K34: ='2_Issue Register'!W32 -> Within 90 days, scope, owners and design principles are agreed; full career architecture is sequenced after higher-priority scaling foundations.
B35: ='2_Issue Register'!B33 -> WFP-04 | C35: ='2_Issue Register'!C33 -> Firm-wide titles and pay bands do not map cleanly to DI's technical roles. | D35: ='2_Issue Register'!I33 -> Weak or unconfirmed | E35: ='2_Issue Register'!P33 -> P4 — Longer-term | F35: ='2_Issue Register'!O33 -> 49 | G35: =IF('2_Issue Register'!U33<>"",'2_Issue Register'!U33,'2_Issue Register'!T33) -> Post-90 days | H35: ='2_Issue Register'!Q33 -> Requires current-role mapping, external benchmarks and coordination with the Compensation Committee. | I35: ='2_Issue Register'!R33 -> Elena / HR + Director of Operations + pod leads | J35: ='2_Issue Register'!V33 -> Map DI roles to a technology-specific job architecture while preserving Deerfield's firm-wide governance. | K35: ='2_Issue Register'!W33 -> Priority roles have agreed level definitions and market-reference ranges; hiring and compensation decisions use consistent mappings.

Sheet Reference
B2: Quick Reference: What counts as triangulation?
B4: Test | C4: Question to ask yourself | D4: Strong signal looks like | E4: Watch-out
B5: Corroboration | C5: Do multiple independent sources point to the same issue? | D5: 3+ sources, ideally across roles / interfaces | E5: Five comments from one person ≠ five signals
B6: Specificity | C6: Is there concrete evidence rather than only sentiment? | D6: Examples, artifacts, observed behavior or metrics | E6: Treat perception as useful context, not proof
B7: Root cause | C7: Do examples share the same underlying mechanism? | D7: A repeatable process / ownership / capability failure | E7: Don't solve the symptom named by the loudest interviewee
B8: Materiality | C8: Does it affect delivery, controls, talent or ability to scale? | D8: Clear consequence and affected population | E8: Avoid over-weighting annoying but low-impact friction
B9: Counter-evidence | C9: Is there evidence the process works elsewhere? | D9: Known exceptions help narrow root cause | E9: Actively look for disconfirming evidence
